{
"meta":{"test_sets":[],"test_metrics":[],"learn_metrics":[{"best_value":"Min","name":"RMSE"}],"launch_mode":"Train","parameters":"","iteration_count":1000,"learn_sets":["learn"],"name":"experiment"},
"iterations":[
{"learn":[0.4888957427],"iteration":0,"passed_time":0.0887247903,"remaining_time":88.63606551},
{"learn":[0.4797936096],"iteration":1,"passed_time":0.1034667773,"remaining_time":51.62992185},
{"learn":[0.4724738399],"iteration":2,"passed_time":0.1178752304,"remaining_time":39.17386823},
{"learn":[0.4663576969],"iteration":3,"passed_time":0.133370908,"remaining_time":33.20935608},
{"learn":[0.4615406353],"iteration":4,"passed_time":0.1476276146,"remaining_time":29.37789531},
{"learn":[0.4573494771],"iteration":5,"passed_time":0.161474081,"remaining_time":26.75087275},
{"learn":[0.453960731],"iteration":6,"passed_time":0.1752494656,"remaining_time":24.86038848},
{"learn":[0.4511595809],"iteration":7,"passed_time":0.1891794717,"remaining_time":23.45825449},
{"learn":[0.4488575258],"iteration":8,"passed_time":0.2035095933,"remaining_time":22.40866744},
{"learn":[0.4469308556],"iteration":9,"passed_time":0.2175498884,"remaining_time":21.53743895},
{"learn":[0.4452146264],"iteration":10,"passed_time":0.2359732472,"remaining_time":21.21614013},
{"learn":[0.4438150314],"iteration":11,"passed_time":0.2493290167,"remaining_time":20.52808904},
{"learn":[0.442616921],"iteration":12,"passed_time":0.2633511456,"remaining_time":19.99442928},
{"learn":[0.4414921801],"iteration":13,"passed_time":0.2777698901,"remaining_time":19.56293655},
{"learn":[0.4405956163],"iteration":14,"passed_time":0.2916711885,"remaining_time":19.15307471},
{"learn":[0.4397262386],"iteration":15,"passed_time":0.3052669107,"remaining_time":18.77391501},
{"learn":[0.439053213],"iteration":16,"passed_time":0.3192457073,"remaining_time":18.45991354},
{"learn":[0.438387987],"iteration":17,"passed_time":0.3330013007,"remaining_time":18.16707096},
{"learn":[0.4378593682],"iteration":18,"passed_time":0.3476431234,"remaining_time":17.94936337},
{"learn":[0.4373871621],"iteration":19,"passed_time":0.363661372,"remaining_time":17.81940723},
{"learn":[0.4369641547],"iteration":20,"passed_time":0.3791356751,"remaining_time":17.67494409},
{"learn":[0.436480535],"iteration":21,"passed_time":0.3948769719,"remaining_time":17.5540763},
{"learn":[0.4361343061],"iteration":22,"passed_time":0.4083150311,"remaining_time":17.34451241},
{"learn":[0.4358088342],"iteration":23,"passed_time":0.4228692725,"remaining_time":17.19668375},
{"learn":[0.4354963148],"iteration":24,"passed_time":0.4361352941,"remaining_time":17.00927647},
{"learn":[0.4352269062],"iteration":25,"passed_time":0.4491348637,"remaining_time":16.82528297},
{"learn":[0.434948327],"iteration":26,"passed_time":0.4640339719,"remaining_time":16.72240943},
{"learn":[0.4346981828],"iteration":27,"passed_time":0.4788074165,"remaining_time":16.62145746},
{"learn":[0.4344996176],"iteration":28,"passed_time":0.4920188977,"remaining_time":16.47414999},
{"learn":[0.4342739358],"iteration":29,"passed_time":0.5063107703,"remaining_time":16.37071491},
{"learn":[0.4340777539],"iteration":30,"passed_time":0.5189418901,"remaining_time":16.22111908},
{"learn":[0.4338591469],"iteration":31,"passed_time":0.5328031478,"remaining_time":16.11729522},
{"learn":[0.4336325639],"iteration":32,"passed_time":0.5461869167,"remaining_time":16.00493177},
{"learn":[0.4334630725],"iteration":33,"passed_time":0.5592784007,"remaining_time":15.89008633},
{"learn":[0.4333137011],"iteration":34,"passed_time":0.5749827817,"remaining_time":15.8530967},
{"learn":[0.4331691121],"iteration":35,"passed_time":0.5885236719,"remaining_time":15.7593561},
{"learn":[0.4330377388],"iteration":36,"passed_time":0.6011317507,"remaining_time":15.64567232},
{"learn":[0.4328811789],"iteration":37,"passed_time":0.6156924502,"remaining_time":15.58674045},
{"learn":[0.4327405686],"iteration":38,"passed_time":0.6295077506,"remaining_time":15.51171662},
{"learn":[0.4326277604],"iteration":39,"passed_time":0.6435880448,"remaining_time":15.44611307},
{"learn":[0.4324891702],"iteration":40,"passed_time":0.656546032,"remaining_time":15.35677182},
{"learn":[0.4323560501],"iteration":41,"passed_time":0.6688266184,"remaining_time":15.25561668},
{"learn":[0.4322611341],"iteration":42,"passed_time":0.6813345745,"remaining_time":15.16365553},
{"learn":[0.4321466468],"iteration":43,"passed_time":0.6951421668,"remaining_time":15.10354344},
{"learn":[0.4320113858],"iteration":44,"passed_time":0.7089388009,"remaining_time":15.04525678},
{"learn":[0.4319197872],"iteration":45,"passed_time":0.7241622766,"remaining_time":15.01849591},
{"learn":[0.4317970976],"iteration":46,"passed_time":0.7395168741,"remaining_time":14.9948847},
{"learn":[0.4317074756],"iteration":47,"passed_time":0.7523074903,"remaining_time":14.92076522},
{"learn":[0.4316123061],"iteration":48,"passed_time":0.7662163718,"remaining_time":14.87085244},
{"learn":[0.4315175203],"iteration":49,"passed_time":0.779658556,"remaining_time":14.81351256},
{"learn":[0.43145364],"iteration":50,"passed_time":0.7930405332,"remaining_time":14.75677384},
{"learn":[0.4313601314],"iteration":51,"passed_time":0.8068395423,"remaining_time":14.7093055},
{"learn":[0.4312597813],"iteration":52,"passed_time":0.8202823931,"remaining_time":14.65674389},
{"learn":[0.4311839757],"iteration":53,"passed_time":0.8338805736,"remaining_time":14.60835227},
{"learn":[0.4311124877],"iteration":54,"passed_time":0.8476964573,"remaining_time":14.5649664},
{"learn":[0.4310517226],"iteration":55,"passed_time":0.8603470351,"remaining_time":14.50299288},
{"learn":[0.4309639825],"iteration":56,"passed_time":0.8744748281,"remaining_time":14.46718882},
{"learn":[0.4308873947],"iteration":57,"passed_time":0.8875231465,"remaining_time":14.41460007},
{"learn":[0.4308362796],"iteration":58,"passed_time":0.9037312657,"remaining_time":14.41374781},
{"learn":[0.4307729927],"iteration":59,"passed_time":0.9170019539,"remaining_time":14.36636394},
{"learn":[0.4306949075],"iteration":60,"passed_time":0.9309860003,"remaining_time":14.33107958},
{"learn":[0.4306345573],"iteration":61,"passed_time":0.9438684893,"remaining_time":14.27981682},
{"learn":[0.4305652025],"iteration":62,"passed_time":0.9577019559,"remaining_time":14.24391639},
{"learn":[0.4305023586],"iteration":63,"passed_time":0.9711265988,"remaining_time":14.20272651},
{"learn":[0.4304369676],"iteration":64,"passed_time":0.9838590497,"remaining_time":14.15243402},
{"learn":[0.4303737104],"iteration":65,"passed_time":0.9971121966,"remaining_time":14.11064836},
{"learn":[0.4303207519],"iteration":66,"passed_time":1.010784792,"remaining_time":14.07555539},
{"learn":[0.4302647286],"iteration":67,"passed_time":1.024080396,"remaining_time":14.03592543},
{"learn":[0.4301998719],"iteration":68,"passed_time":1.036894595,"remaining_time":13.99056331},
{"learn":[0.4301347373],"iteration":69,"passed_time":1.050130118,"remaining_time":13.9517287},
{"learn":[0.4300868265],"iteration":70,"passed_time":1.063726756,"remaining_time":13.91834024},
{"learn":[0.430048078],"iteration":71,"passed_time":1.076251962,"remaining_time":13.87169196},
{"learn":[0.429989474],"iteration":72,"passed_time":1.091079989,"remaining_time":13.85522123},
{"learn":[0.4299357066],"iteration":73,"passed_time":1.105637772,"remaining_time":13.8354132},
{"learn":[0.429893923],"iteration":74,"passed_time":1.117920483,"remaining_time":13.78768596},
{"learn":[0.4298525479],"iteration":75,"passed_time":1.131701618,"remaining_time":13.75910914},
{"learn":[0.4298104325],"iteration":76,"passed_time":1.145086261,"remaining_time":13.72616389},
{"learn":[0.4297711213],"iteration":77,"passed_time":1.158485197,"remaining_time":13.69388912},
{"learn":[0.4297357169],"iteration":78,"passed_time":1.171060401,"remaining_time":13.65248898},
{"learn":[0.4296789682],"iteration":79,"passed_time":1.186229753,"remaining_time":13.64164216},
{"learn":[0.4296423816],"iteration":80,"passed_time":1.204336328,"remaining_time":13.6640134},
{"learn":[0.4295940218],"iteration":81,"passed_time":1.21712761,"remaining_time":13.62589203},
{"learn":[0.4295367585],"iteration":82,"passed_time":1.23056842,"remaining_time":13.59555712},
{"learn":[0.429502836],"iteration":83,"passed_time":1.243674362,"remaining_time":13.5619728},
{"learn":[0.4294546729],"iteration":84,"passed_time":1.257617492,"remaining_time":13.53788242},
{"learn":[0.4294085189],"iteration":85,"passed_time":1.269982285,"remaining_time":13.49725359},
{"learn":[0.4293513529],"iteration":86,"passed_time":1.284837436,"remaining_time":13.48340896},
{"learn":[0.4293191466],"iteration":87,"passed_time":1.298905981,"remaining_time":13.46138925},
{"learn":[0.429276708],"iteration":88,"passed_time":1.313973127,"remaining_time":13.44976987},
{"learn":[0.4292446281],"iteration":89,"passed_time":1.326519623,"remaining_time":13.4125873},
{"learn":[0.4292027189],"iteration":90,"passed_time":1.339739854,"remaining_time":13.38267613},
{"learn":[0.4291695361],"iteration":91,"passed_time":1.353369993,"remaining_time":13.3571734},
{"learn":[0.4291268885],"iteration":92,"passed_time":1.366855926,"remaining_time":13.33051962},
{"learn":[0.4290857038],"iteration":93,"passed_time":1.381322877,"remaining_time":13.31360135},
{"learn":[0.4290487897],"iteration":94,"passed_time":1.394446194,"remaining_time":13.2839348},
{"learn":[0.4290025352],"iteration":95,"passed_time":1.407617218,"remaining_time":13.25506214},
{"learn":[0.4289597994],"iteration":96,"passed_time":1.420127882,"remaining_time":13.22036575},
{"learn":[0.4289227639],"iteration":97,"passed_time":1.434235259,"remaining_time":13.20081841},
{"learn":[0.4288998153],"iteration":98,"passed_time":1.447715317,"remaining_time":13.17567173},
{"learn":[0.4288629474],"iteration":99,"passed_time":1.461098295,"remaining_time":13.14988465},
{"learn":[0.4288243457],"iteration":100,"passed_time":1.473716415,"remaining_time":13.11753522},
{"learn":[0.4287872799],"iteration":101,"passed_time":1.487502174,"remaining_time":13.09585248},
{"learn":[0.4287643137],"iteration":102,"passed_time":1.49987105,"remaining_time":13.06198381},
{"learn":[0.4287306033],"iteration":103,"passed_time":1.512469421,"remaining_time":13.03050578},
{"learn":[0.4286995453],"iteration":104,"passed_time":1.52500446,"remaining_time":12.99884754},
{"learn":[0.4286630948],"iteration":105,"passed_time":1.538625015,"remaining_time":12.97670531},
{"learn":[0.4286264454],"iteration":106,"passed_time":1.552003325,"remaining_time":12.95270065},
{"learn":[0.4285928058],"iteration":107,"passed_time":1.566354988,"remaining_time":12.93693194},
{"learn":[0.4285498147],"iteration":108,"passed_time":1.581201764,"remaining_time":12.92523644},
{"learn":[0.4285219928],"iteration":109,"passed_time":1.594732363,"remaining_time":12.90283457},
{"learn":[0.4284929127],"iteration":110,"passed_time":1.607763849,"remaining_time":12.87659515},
{"learn":[0.4284576501],"iteration":111,"passed_time":1.622334173,"remaining_time":12.86279237},
{"learn":[0.4284316941],"iteration":112,"passed_time":1.634981584,"remaining_time":12.83388199},
{"learn":[0.4284029791],"iteration":113,"passed_time":1.648401685,"remaining_time":12.81126222},
{"learn":[0.4283726666],"iteration":114,"passed_time":1.660674772,"remaining_time":12.77997542},
{"learn":[0.428335772],"iteration":115,"passed_time":1.67368205,"remaining_time":12.75461148},
{"learn":[0.4283040576],"iteration":116,"passed_time":1.687974422,"remaining_time":12.73915739},
{"learn":[0.4282765639],"iteration":117,"passed_time":1.701133113,"remaining_time":12.7152492},
{"learn":[0.4282508423],"iteration":118,"passed_time":1.716720789,"remaining_time":12.70950433},
{"learn":[0.4282123068],"iteration":119,"passed_time":1.73174906,"remaining_time":12.69949311},
{"learn":[0.4281821867],"iteration":120,"passed_time":1.744718047,"remaining_time":12.67443937},
{"learn":[0.4281623458],"iteration":121,"passed_time":1.758442975,"remaining_time":12.65502403},
{"learn":[0.4281306276],"iteration":122,"passed_time":1.77448189,"remaining_time":12.65220014},
{"learn":[0.4281091094],"iteration":123,"passed_time":1.787991864,"remaining_time":12.63129736},
{"learn":[0.4280761878],"iteration":124,"passed_time":1.802182364,"remaining_time":12.61527655},
{"learn":[0.4280391654],"iteration":125,"passed_time":1.824614795,"remaining_time":12.65645501},
{"learn":[0.4280017193],"iteration":126,"passed_time":1.848973889,"remaining_time":12.70987563},
{"learn":[0.427975905],"iteration":127,"passed_time":1.868981128,"remaining_time":12.73243393},
{"learn":[0.4279402399],"iteration":128,"passed_time":1.888291924,"remaining_time":12.74962997},
{"learn":[0.4279148921],"iteration":129,"passed_time":1.912747641,"remaining_time":12.80069575},
{"learn":[0.4278824802],"iteration":130,"passed_time":1.932145727,"remaining_time":12.81705829},
{"learn":[0.4278546979],"iteration":131,"passed_time":1.953403227,"remaining_time":12.84510607},
{"learn":[0.427831928],"iteration":132,"passed_time":1.970781236,"remaining_time":12.84712279},
{"learn":[0.4278029992],"iteration":133,"passed_time":1.984325667,"remaining_time":12.82407484},
{"learn":[0.4277707532],"iteration":134,"passed_time":1.997893515,"remaining_time":12.80131771},
{"learn":[0.4277427024],"iteration":135,"passed_time":2.011026248,"remaining_time":12.77593146},
{"learn":[0.4277145233],"iteration":136,"passed_time":2.024104024,"remaining_time":12.75037791},
{"learn":[0.4276916489],"iteration":137,"passed_time":2.037762454,"remaining_time":12.72863214},
{"learn":[0.427658943],"iteration":138,"passed_time":2.051560546,"remaining_time":12.70786784},
{"learn":[0.4276348613],"iteration":139,"passed_time":2.064276622,"remaining_time":12.68055639},
{"learn":[0.4276119304],"iteration":140,"passed_time":2.077192235,"remaining_time":12.65466759},
{"learn":[0.4275923803],"iteration":141,"passed_time":2.089650901,"remaining_time":12.62620051},
{"learn":[0.4275633551],"iteration":142,"passed_time":2.103993397,"remaining_time":12.60924714},
{"learn":[0.4275363095],"iteration":143,"passed_time":2.119774902,"remaining_time":12.60088414},
{"learn":[0.4275034237],"iteration":144,"passed_time":2.133336958,"remaining_time":12.57933172},
{"learn":[0.4274775962],"iteration":145,"passed_time":2.146879598,"remaining_time":12.55777518},
{"learn":[0.4274465803],"iteration":146,"passed_time":2.161279218,"remaining_time":12.5413005},
{"learn":[0.4274161395],"iteration":147,"passed_time":2.174780776,"remaining_time":12.51968393},
{"learn":[0.4273960703],"iteration":148,"passed_time":2.187846219,"remaining_time":12.49568545},
{"learn":[0.4273810124],"iteration":149,"passed_time":2.200430715,"remaining_time":12.46910738},
{"learn":[0.4273591739],"iteration":150,"passed_time":2.214309514,"remaining_time":12.4499919},
{"learn":[0.4273388875],"iteration":151,"passed_time":2.227302792,"remaining_time":12.42600505},
{"learn":[0.4273122725],"iteration":152,"passed_time":2.241545082,"remaining_time":12.40907637},
{"learn":[0.427293302],"iteration":153,"passed_time":2.254599067,"remaining_time":12.38565462},
{"learn":[0.4272662777],"iteration":154,"passed_time":2.267380058,"remaining_time":12.36087838},
{"learn":[0.4272437401],"iteration":155,"passed_time":2.280086593,"remaining_time":12.33585311},
{"learn":[0.427208996],"iteration":156,"passed_time":2.294559378,"remaining_time":12.32046851},
{"learn":[0.4271892601],"iteration":157,"passed_time":2.308378928,"remaining_time":12.30161429},
{"learn":[0.4271715003],"iteration":158,"passed_time":2.321323749,"remaining_time":12.27819669},
{"learn":[0.4271474356],"iteration":159,"passed_time":2.334738517,"remaining_time":12.25737722},
{"learn":[0.4271276385],"iteration":160,"passed_time":2.347622048,"remaining_time":12.23388136},
{"learn":[0.4271022373],"iteration":161,"passed_time":2.365886786,"remaining_time":12.23835263},
{"learn":[0.4270767495],"iteration":162,"passed_time":2.379784709,"remaining_time":12.22012148},
{"learn":[0.427055915],"iteration":163,"passed_time":2.392750738,"remaining_time":12.19719278},
{"learn":[0.4270397709],"iteration":164,"passed_time":2.405337275,"remaining_time":12.17246439},
{"learn":[0.4270221316],"iteration":165,"passed_time":2.419977931,"remaining_time":12.15820238},
{"learn":[0.4269935465],"iteration":166,"passed_time":2.433483031,"remaining_time":12.13827164},
{"learn":[0.4269562764],"iteration":167,"passed_time":2.447550533,"remaining_time":12.12120264},
{"learn":[0.4269282256],"iteration":168,"passed_time":2.461714284,"remaining_time":12.10464243},
{"learn":[0.4268977549],"iteration":169,"passed_time":2.474906016,"remaining_time":12.08336466},
{"learn":[0.4268742216],"iteration":170,"passed_time":2.488098872,"remaining_time":12.06218693},
{"learn":[0.4268528147],"iteration":171,"passed_time":2.500899113,"remaining_time":12.03921201},
{"learn":[0.4268229441],"iteration":172,"passed_time":2.513332071,"remaining_time":12.01459898},
{"learn":[0.426796058],"iteration":173,"passed_time":2.527691567,"remaining_time":11.99927146},
{"learn":[0.4267775792],"iteration":174,"passed_time":2.541141334,"remaining_time":11.97966629},
{"learn":[0.4267451569],"iteration":175,"passed_time":2.555604203,"remaining_time":11.96487422},
{"learn":[0.4267256007],"iteration":176,"passed_time":2.56798487,"remaining_time":11.94040423},
{"learn":[0.4267002331],"iteration":177,"passed_time":2.581142561,"remaining_time":11.91965834},
{"learn":[0.4266765555],"iteration":178,"passed_time":2.595061942,"remaining_time":11.90249081},
{"learn":[0.4266547237],"iteration":179,"passed_time":2.610223378,"remaining_time":11.89101761},
{"learn":[0.4266272139],"iteration":180,"passed_time":2.62354794,"remaining_time":11.87119206},
{"learn":[0.4266143029],"iteration":181,"passed_time":2.635970773,"remaining_time":11.84738512},
{"learn":[0.4265990129],"iteration":182,"passed_time":2.649092048,"remaining_time":11.82682078},
{"learn":[0.4265799914],"iteration":183,"passed_time":2.663211466,"remaining_time":11.81076389},
{"learn":[0.4265663017],"iteration":184,"passed_time":2.675276474,"remaining_time":11.78567744},
{"learn":[0.4265486],"iteration":185,"passed_time":2.688213712,"remaining_time":11.76454818},
{"learn":[0.4265303763],"iteration":186,"passed_time":2.701382819,"remaining_time":11.74451461},
{"learn":[0.4265054433],"iteration":187,"passed_time":2.716232262,"remaining_time":11.73181169},
{"learn":[0.4264943345],"iteration":188,"passed_time":2.728351436,"remaining_time":11.70737045},
{"learn":[0.4264793445],"iteration":189,"passed_time":2.743083798,"remaining_time":11.69419935},
{"learn":[0.4264650567],"iteration":190,"passed_time":2.756588564,"remaining_time":11.67581229},
{"learn":[0.4264520296],"iteration":191,"passed_time":2.771096973,"remaining_time":11.66169976},
{"learn":[0.4264261047],"iteration":192,"passed_time":2.785877917,"remaining_time":11.64872269},
{"learn":[0.4264094616],"iteration":193,"passed_time":2.798942319,"remaining_time":11.62859541},
{"learn":[0.4263962541],"iteration":194,"passed_time":2.814578868,"remaining_time":11.61915892},
{"learn":[0.4263693652],"iteration":195,"passed_time":2.830566826,"remaining_time":11.61110065},
{"learn":[0.4263560609],"iteration":196,"passed_time":2.844915822,"remaining_time":11.59628124},
{"learn":[0.4263373564],"iteration":197,"passed_time":2.85951602,"remaining_time":11.58248408},
{"learn":[0.4263155108],"iteration":198,"passed_time":2.872497465,"remaining_time":11.56216316},
{"learn":[0.4263014362],"iteration":199,"passed_time":2.887111289,"remaining_time":11.54844515},
{"learn":[0.4262843397],"iteration":200,"passed_time":2.901231374,"remaining_time":11.53275556},
{"learn":[0.4262649596],"iteration":201,"passed_time":2.913912826,"remaining_time":11.51139819},
{"learn":[0.4262534382],"iteration":202,"passed_time":2.925935918,"remaining_time":11.48754151},
{"learn":[0.426238521],"iteration":203,"passed_time":2.938963487,"remaining_time":11.46772027},
{"learn":[0.4262230862],"iteration":204,"passed_time":2.952097095,"remaining_time":11.44837654},
{"learn":[0.4262085527],"iteration":205,"passed_time":2.965778607,"remaining_time":11.43120492},
{"learn":[0.4261957956],"iteration":206,"passed_time":2.978673387,"remaining_time":11.41105312},
{"learn":[0.4261747307],"iteration":207,"passed_time":2.99281843,"remaining_time":11.39573171},
{"learn":[0.4261600886],"iteration":208,"passed_time":3.006121992,"remaining_time":11.37723682},
{"learn":[0.42613822],"iteration":209,"passed_time":3.020081206,"remaining_time":11.36125787},
{"learn":[0.4261215261],"iteration":210,"passed_time":3.034237207,"remaining_time":11.34603392},
{"learn":[0.4261051632],"iteration":211,"passed_time":3.046905951,"remaining_time":11.32529193},
{"learn":[0.4260890951],"iteration":212,"passed_time":3.060246471,"remaining_time":11.30710785},
{"learn":[0.4260694231],"iteration":213,"passed_time":3.073580866,"remaining_time":11.28894654},
{"learn":[0.4260592368],"iteration":214,"passed_time":3.085599125,"remaining_time":11.26602471},
{"learn":[0.4260417125],"iteration":215,"passed_time":3.099102099,"remaining_time":11.24859281},
{"learn":[0.4260242279],"iteration":216,"passed_time":3.114061915,"remaining_time":11.23645382},
{"learn":[0.4260045364],"iteration":217,"passed_time":3.128282372,"remaining_time":11.22163677},
{"learn":[0.4259875813],"iteration":218,"passed_time":3.140925117,"remaining_time":11.2011987},
{"learn":[0.4259765363],"iteration":219,"passed_time":3.153931686,"remaining_time":11.18212143},
{"learn":[0.4259670258],"iteration":220,"passed_time":3.16694063,"remaining_time":11.16310747},
{"learn":[0.4259417163],"iteration":221,"passed_time":3.180320566,"remaining_time":11.14544775},
{"learn":[0.4259308306],"iteration":222,"passed_time":3.193027476,"remaining_time":11.12548138},
{"learn":[0.4259128727],"iteration":223,"passed_time":3.206671697,"remaining_time":11.10882695},
{"learn":[0.4259011569],"iteration":224,"passed_time":3.220089132,"remaining_time":11.09141812},
{"learn":[0.4258870642],"iteration":225,"passed_time":3.233126367,"remaining_time":11.07274251},
{"learn":[0.4258644123],"iteration":226,"passed_time":3.246666757,"remaining_time":11.05582997},
{"learn":[0.4258521622],"iteration":227,"passed_time":3.259551579,"remaining_time":11.03672728},
{"learn":[0.4258278081],"iteration":228,"passed_time":3.273858452,"remaining_time":11.02246666},
{"learn":[0.4258151157],"iteration":229,"passed_time":3.287197097,"remaining_time":11.00496419},
{"learn":[0.4257963681],"iteration":230,"passed_time":3.300426369,"remaining_time":10.98713367},
{"learn":[0.4257731276],"iteration":231,"passed_time":3.31458937,"remaining_time":10.97243378},
{"learn":[0.4257501431],"iteration":232,"passed_time":3.327646646,"remaining_time":10.95409862},
{"learn":[0.4257276182],"iteration":233,"passed_time":3.34173894,"remaining_time":10.9391967},
{"learn":[0.4257011188],"iteration":234,"passed_time":3.359638853,"remaining_time":10.93669669},
{"learn":[0.4256852783],"iteration":235,"passed_time":3.374578835,"remaining_time":10.92448403},
{"learn":[0.4256687134],"iteration":236,"passed_time":3.388389761,"remaining_time":10.90861345},
{"learn":[0.4256533037],"iteration":237,"passed_time":3.401070838,"remaining_time":10.88914277},
{"learn":[0.4256358017],"iteration":238,"passed_time":3.414319026,"remaining_time":10.87153464},
{"learn":[0.4256228017],"iteration":239,"passed_time":3.428375154,"remaining_time":10.85652132},
{"learn":[0.4256076452],"iteration":240,"passed_time":3.442086957,"remaining_time":10.84043154},
{"learn":[0.4255940549],"iteration":241,"passed_time":3.455540766,"remaining_time":10.82355331},
{"learn":[0.4255768218],"iteration":242,"passed_time":3.469392691,"remaining_time":10.80794348},
{"learn":[0.4255646813],"iteration":243,"passed_time":3.482588631,"remaining_time":10.79031559},
{"learn":[0.4255483743],"iteration":244,"passed_time":3.495466911,"remaining_time":10.77174497},
{"learn":[0.4255332735],"iteration":245,"passed_time":3.509015676,"remaining_time":10.75527569},
{"learn":[0.425511713],"iteration":246,"passed_time":3.522107827,"remaining_time":10.73743803},
{"learn":[0.4254922144],"iteration":247,"passed_time":3.535522095,"remaining_time":10.72061539},
{"learn":[0.4254773958],"iteration":248,"passed_time":3.548085883,"remaining_time":10.70125501},
{"learn":[0.425459643],"iteration":249,"passed_time":3.562097887,"remaining_time":10.68629366},
{"learn":[0.4254421918],"iteration":250,"passed_time":3.576928164,"remaining_time":10.67378165},
{"learn":[0.4254254603],"iteration":251,"passed_time":3.590473221,"remaining_time":10.65743639},
{"learn":[0.4254126104],"iteration":252,"passed_time":3.604249064,"remaining_time":10.64179467},
{"learn":[0.4253947543],"iteration":253,"passed_time":3.618162737,"remaining_time":10.62657245},
{"learn":[0.4253823808],"iteration":254,"passed_time":3.631078892,"remaining_time":10.60844617},
{"learn":[0.425369487],"iteration":255,"passed_time":3.644843068,"remaining_time":10.59282517},
{"learn":[0.4253541033],"iteration":256,"passed_time":3.657927552,"remaining_time":10.57525359},
{"learn":[0.4253440864],"iteration":257,"passed_time":3.670274596,"remaining_time":10.55559593},
{"learn":[0.4253335097],"iteration":258,"passed_time":3.683626032,"remaining_time":10.5388683},
{"learn":[0.4253221841],"iteration":259,"passed_time":3.696770098,"remaining_time":10.52157643},
{"learn":[0.4253068059],"iteration":260,"passed_time":3.71252302,"remaining_time":10.51170311},
{"learn":[0.425292322],"iteration":261,"passed_time":3.726837058,"remaining_time":10.49773187},
{"learn":[0.4252794565],"iteration":262,"passed_time":3.739806879,"remaining_time":10.47999114},
{"learn":[0.4252682564],"iteration":263,"passed_time":3.753155023,"remaining_time":10.46334128},
{"learn":[0.4252508883],"iteration":264,"passed_time":3.768066298,"remaining_time":10.45105181},
{"learn":[0.4252366115],"iteration":265,"passed_time":3.781837558,"remaining_time":10.43559687},
{"learn":[0.4252191848],"iteration":266,"passed_time":3.795605193,"remaining_time":10.42014459},
{"learn":[0.4252048749],"iteration":267,"passed_time":3.809160207,"remaining_time":10.40412415},
{"learn":[0.425191344],"iteration":268,"passed_time":3.822276399,"remaining_time":10.38692955},
{"learn":[0.4251814573],"iteration":269,"passed_time":3.835260719,"remaining_time":10.36940861},
{"learn":[0.4251693213],"iteration":270,"passed_time":3.84785434,"remaining_time":10.35087016},
{"learn":[0.4251585268],"iteration":271,"passed_time":3.861155819,"remaining_time":10.33426999},
{"learn":[0.4251452783],"iteration":272,"passed_time":3.874943203,"remaining_time":10.31898794},
{"learn":[0.42513639],"iteration":273,"passed_time":3.888034771,"remaining_time":10.30187315},
{"learn":[0.4251275157],"iteration":274,"passed_time":3.899903242,"remaining_time":10.28156309},
{"learn":[0.4251168716],"iteration":275,"passed_time":3.913224096,"remaining_time":10.26512408},
{"learn":[0.4251010597],"iteration":276,"passed_time":3.927660215,"remaining_time":10.25161854},
{"learn":[0.4250856542],"iteration":277,"passed_time":3.941256145,"remaining_time":10.23592423},
{"learn":[0.425071318],"iteration":278,"passed_time":3.955284399,"remaining_time":10.22136219},
{"learn":[0.4250586964],"iteration":279,"passed_time":3.968282052,"remaining_time":10.20415385},
{"learn":[0.4250464198],"iteration":280,"passed_time":3.981703028,"remaining_time":10.18805864},
{"learn":[0.4250389802],"iteration":281,"passed_time":3.993427336,"remaining_time":10.16766251},
{"learn":[0.4250306657],"iteration":282,"passed_time":4.005615341,"remaining_time":10.14850247},
{"learn":[0.4250178553],"iteration":283,"passed_time":4.018767991,"remaining_time":10.13182353},
{"learn":[0.4250035983],"iteration":284,"passed_time":4.033677057,"remaining_time":10.11957577},
{"learn":[0.4249925176],"iteration":285,"passed_time":4.046559796,"remaining_time":10.10225068},
{"learn":[0.4249785473],"iteration":286,"passed_time":4.059950648,"remaining_time":10.08621886},
{"learn":[0.424967758],"iteration":287,"passed_time":4.073655534,"remaining_time":10.07098174},
{"learn":[0.4249497991],"iteration":288,"passed_time":4.088081529,"remaining_time":10.0575293},
{"learn":[0.4249388674],"iteration":289,"passed_time":4.1010151,"remaining_time":10.04041628},
{"learn":[0.4249269468],"iteration":290,"passed_time":4.115517842,"remaining_time":10.02715516},
{"learn":[0.4249157509],"iteration":291,"passed_time":4.128934902,"remaining_time":10.01125312},
{"learn":[0.4249042808],"iteration":292,"passed_time":4.142772619,"remaining_time":9.996383077},
{"learn":[0.424894217],"iteration":293,"passed_time":4.155971559,"remaining_time":9.979986124},
{"learn":[0.4248834209],"iteration":294,"passed_time":4.169155457,"remaining_time":9.963574906},
{"learn":[0.4248661379],"iteration":295,"passed_time":4.183072339,"remaining_time":9.948928805},
{"learn":[0.4248534688],"iteration":296,"passed_time":4.196015576,"remaining_time":9.931982997},
{"learn":[0.4248440552],"iteration":297,"passed_time":4.208944064,"remaining_time":9.915029305},
{"learn":[0.4248280128],"iteration":298,"passed_time":4.222231043,"remaining_time":9.898943015},
{"learn":[0.4248175472],"iteration":299,"passed_time":4.235298903,"remaining_time":9.882364107},
{"learn":[0.4248060734],"iteration":300,"passed_time":4.248632381,"remaining_time":9.866425364},
{"learn":[0.4247951199],"iteration":301,"passed_time":4.261459372,"remaining_time":9.84933325},
{"learn":[0.4247853351],"iteration":302,"passed_time":4.274707977,"remaining_time":9.833239142},
{"learn":[0.4247738103],"iteration":303,"passed_time":4.288385156,"remaining_time":9.818144962},
{"learn":[0.4247652349],"iteration":304,"passed_time":4.301123065,"remaining_time":9.800919771},
{"learn":[0.4247566675],"iteration":305,"passed_time":4.31431938,"remaining_time":9.784763561},
{"learn":[0.4247462235],"iteration":306,"passed_time":4.328389882,"remaining_time":9.770599963},
{"learn":[0.4247302603],"iteration":307,"passed_time":4.342715671,"remaining_time":9.757010533},
{"learn":[0.4247209616],"iteration":308,"passed_time":4.356191813,"remaining_time":9.741516319},
{"learn":[0.4247104462],"iteration":309,"passed_time":4.372557845,"remaining_time":9.732467461},
{"learn":[0.4246978981],"iteration":310,"passed_time":4.386360104,"remaining_time":9.717691677},
{"learn":[0.4246868957],"iteration":311,"passed_time":4.398810978,"remaining_time":9.699942156},
{"learn":[0.4246750628],"iteration":312,"passed_time":4.413748918,"remaining_time":9.687685326},
{"learn":[0.4246637414],"iteration":313,"passed_time":4.427316225,"remaining_time":9.672416975},
{"learn":[0.4246523972],"iteration":314,"passed_time":4.440499582,"remaining_time":9.656324487},
{"learn":[0.424641356],"iteration":315,"passed_time":4.460750564,"remaining_time":9.655548689},
{"learn":[0.4246265258],"iteration":316,"passed_time":4.473862464,"remaining_time":9.639268338},
{"learn":[0.4246157973],"iteration":317,"passed_time":4.489211354,"remaining_time":9.627805482},
{"learn":[0.4246079851],"iteration":318,"passed_time":4.511335792,"remaining_time":9.630782679},
{"learn":[0.4245963457],"iteration":319,"passed_time":4.525968907,"remaining_time":9.617683927},
{"learn":[0.4245885027],"iteration":320,"passed_time":4.538802355,"remaining_time":9.600768845},
{"learn":[0.424581135],"iteration":321,"passed_time":4.551877215,"remaining_time":9.584387427},
{"learn":[0.4245696853],"iteration":322,"passed_time":4.566563661,"remaining_time":9.57140433},
{"learn":[0.424559839],"iteration":323,"passed_time":4.580762161,"remaining_time":9.557392657},
{"learn":[0.4245516148],"iteration":324,"passed_time":4.595212613,"remaining_time":9.54390312},
{"learn":[0.4245429136],"iteration":325,"passed_time":4.609012164,"remaining_time":9.529061958},
{"learn":[0.4245241474],"iteration":326,"passed_time":4.623295287,"remaining_time":9.515222409},
{"learn":[0.4245109756],"iteration":327,"passed_time":4.636017154,"remaining_time":9.498181487},
{"learn":[0.4245005783],"iteration":328,"passed_time":4.650207404,"remaining_time":9.484161606},
{"learn":[0.4244910156],"iteration":329,"passed_time":4.66322814,"remaining_time":9.467766224},
{"learn":[0.4244821691],"iteration":330,"passed_time":4.676045964,"remaining_time":9.450981117},
{"learn":[0.4244736247],"iteration":331,"passed_time":4.689615812,"remaining_time":9.435733019},
{"learn":[0.4244595226],"iteration":332,"passed_time":4.707833925,"remaining_time":9.42980549},
{"learn":[0.4244516632],"iteration":333,"passed_time":4.721419023,"remaining_time":9.414566075},
{"learn":[0.4244424784],"iteration":334,"passed_time":4.734839791,"remaining_time":9.399010331},
{"learn":[0.4244263808],"iteration":335,"passed_time":4.750282261,"remaining_time":9.387462564},
{"learn":[0.4244168617],"iteration":336,"passed_time":4.7649415,"remaining_time":9.374350785},
{"learn":[0.4244015444],"iteration":337,"passed_time":4.778729134,"remaining_time":9.359522743},
{"learn":[0.4243930218],"iteration":338,"passed_time":4.791365296,"remaining_time":9.342455636},
{"learn":[0.4243866685],"iteration":339,"passed_time":4.804197536,"remaining_time":9.325795217},
{"learn":[0.4243803852],"iteration":340,"passed_time":4.817049734,"remaining_time":9.30919582},
{"learn":[0.4243717666],"iteration":341,"passed_time":4.830584416,"remaining_time":9.29393142},
{"learn":[0.424362874],"iteration":342,"passed_time":4.84460917,"remaining_time":9.279615815},
{"learn":[0.4243530443],"iteration":343,"passed_time":4.859093955,"remaining_time":9.266179169},
{"learn":[0.4243452287],"iteration":344,"passed_time":4.871737741,"remaining_time":9.249241218},
{"learn":[0.4243359697],"iteration":345,"passed_time":4.885503751,"remaining_time":9.234449286},
{"learn":[0.4243211754],"iteration":346,"passed_time":4.90056298,"remaining_time":9.222096905},
{"learn":[0.4243112706],"iteration":347,"passed_time":4.914054913,"remaining_time":9.206792538},
{"learn":[0.4243037],"iteration":348,"passed_time":4.927416141,"remaining_time":9.19125475},
{"learn":[0.4242944638],"iteration":349,"passed_time":4.940783285,"remaining_time":9.175740387},
{"learn":[0.4242870659],"iteration":350,"passed_time":4.95503795,"remaining_time":9.161879287},
{"learn":[0.4242781806],"iteration":351,"passed_time":4.96808381,"remaining_time":9.145790651},
{"learn":[0.4242693487],"iteration":352,"passed_time":4.98177528,"remaining_time":9.130902568},
{"learn":[0.4242619433],"iteration":353,"passed_time":4.995024052,"remaining_time":9.115213384},
{"learn":[0.424256549],"iteration":354,"passed_time":5.006707486,"remaining_time":9.096693883},
{"learn":[0.4242455005],"iteration":355,"passed_time":5.020739823,"remaining_time":9.082461927},
{"learn":[0.4242395309],"iteration":356,"passed_time":5.035326105,"remaining_time":9.069228812},
{"learn":[0.4242295539],"iteration":357,"passed_time":5.048988618,"remaining_time":9.054331544},
{"learn":[0.4242172557],"iteration":358,"passed_time":5.062293972,"remaining_time":9.038803443},
{"learn":[0.4242084646],"iteration":359,"passed_time":5.075587326,"remaining_time":9.023266358},
{"learn":[0.4241978066],"iteration":360,"passed_time":5.089660662,"remaining_time":9.009122335},
{"learn":[0.4241888821],"iteration":361,"passed_time":5.102578359,"remaining_time":8.992941969},
{"learn":[0.4241827389],"iteration":362,"passed_time":5.115501888,"remaining_time":8.976789815},
{"learn":[0.4241712892],"iteration":363,"passed_time":5.129380021,"remaining_time":8.962323333},
{"learn":[0.4241623298],"iteration":364,"passed_time":5.143890096,"remaining_time":8.948959483},
{"learn":[0.4241482987],"iteration":365,"passed_time":5.157864976,"remaining_time":8.934662281},
{"learn":[0.4241346741],"iteration":366,"passed_time":5.172486341,"remaining_time":8.921481891},
{"learn":[0.4241279682],"iteration":367,"passed_time":5.185815653,"remaining_time":8.906074708},
{"learn":[0.4241168103],"iteration":368,"passed_time":5.201797319,"remaining_time":8.895214386},
{"learn":[0.4241069251],"iteration":369,"passed_time":5.216142524,"remaining_time":8.881539973},
{"learn":[0.42409718],"iteration":370,"passed_time":5.229293465,"remaining_time":8.865837168},
{"learn":[0.4240876366],"iteration":371,"passed_time":5.242274451,"remaining_time":8.84986117},
{"learn":[0.4240799394],"iteration":372,"passed_time":5.25580405,"remaining_time":8.83482343},
{"learn":[0.4240747264],"iteration":373,"passed_time":5.268157385,"remaining_time":8.817824927},
{"learn":[0.4240661834],"iteration":374,"passed_time":5.281740774,"remaining_time":8.80290129},
{"learn":[0.4240563314],"iteration":375,"passed_time":5.295657197,"remaining_time":8.788537476},
{"learn":[0.4240491472],"iteration":376,"passed_time":5.308990384,"remaining_time":8.773212226},
{"learn":[0.4240416517],"iteration":377,"passed_time":5.321495048,"remaining_time":8.75653418},
{"learn":[0.4240305442],"iteration":378,"passed_time":5.335280599,"remaining_time":8.741976919},
{"learn":[0.4240216896],"iteration":379,"passed_time":5.34878449,"remaining_time":8.726964168},
{"learn":[0.4240136816],"iteration":380,"passed_time":5.362133968,"remaining_time":8.711708468},
{"learn":[0.424007803],"iteration":381,"passed_time":5.37513108,"remaining_time":8.695892689},
{"learn":[0.4239979469],"iteration":382,"passed_time":5.388218522,"remaining_time":8.680237149},
{"learn":[0.4239879213],"iteration":383,"passed_time":5.401106636,"remaining_time":8.664275229},
{"learn":[0.4239810415],"iteration":384,"passed_time":5.414873021,"remaining_time":8.649732228},
{"learn":[0.4239729901],"iteration":385,"passed_time":5.429092978,"remaining_time":8.635914738},
{"learn":[0.4239647384],"iteration":386,"passed_time":5.442162046,"remaining_time":8.620272182},
{"learn":[0.423956175],"iteration":387,"passed_time":5.455575773,"remaining_time":8.605186528},
{"learn":[0.4239512285],"iteration":388,"passed_time":5.469196578,"remaining_time":8.590434728},
{"learn":[0.4239445077],"iteration":389,"passed_time":5.48185003,"remaining_time":8.574175689},
{"learn":[0.4239360004],"iteration":390,"passed_time":5.494791476,"remaining_time":8.558383655},
{"learn":[0.4239284291],"iteration":391,"passed_time":5.508151996,"remaining_time":8.543256157},
{"learn":[0.4239160701],"iteration":392,"passed_time":5.523371513,"remaining_time":8.531008928},
{"learn":[0.4239090427],"iteration":393,"passed_time":5.536995151,"remaining_time":8.516292035},
{"learn":[0.4238985523],"iteration":394,"passed_time":5.550713662,"remaining_time":8.501725989},
{"learn":[0.4238878736],"iteration":395,"passed_time":5.564093181,"remaining_time":8.486647176},
{"learn":[0.4238765382],"iteration":396,"passed_time":5.579121495,"remaining_time":8.474081263},
{"learn":[0.4238624331],"iteration":397,"passed_time":5.59410256,"remaining_time":8.46143151},
{"learn":[0.4238492271],"iteration":398,"passed_time":5.609496198,"remaining_time":8.449391516},
{"learn":[0.4238332365],"iteration":399,"passed_time":5.624688591,"remaining_time":8.437032886},
{"learn":[0.4238211615],"iteration":400,"passed_time":5.638109401,"remaining_time":8.422013793},
{"learn":[0.4238123494],"iteration":401,"passed_time":5.651499669,"remaining_time":8.40695722},
{"learn":[0.4238043597],"iteration":402,"passed_time":5.665348719,"remaining_time":8.392588549},
{"learn":[0.4237967709],"iteration":403,"passed_time":5.678680322,"remaining_time":8.377459089},
{"learn":[0.4237884581],"iteration":404,"passed_time":5.694259581,"remaining_time":8.365640619},
{"learn":[0.4237795637],"iteration":405,"passed_time":5.708396832,"remaining_time":8.351693888},
{"learn":[0.4237688267],"iteration":406,"passed_time":5.722763453,"remaining_time":8.338080412},
{"learn":[0.4237583125],"iteration":407,"passed_time":5.736879913,"remaining_time":8.324100266},
{"learn":[0.4237509095],"iteration":408,"passed_time":5.751386114,"remaining_time":8.310682624},
{"learn":[0.4237401814],"iteration":409,"passed_time":5.765932772,"remaining_time":8.297317892},
{"learn":[0.4237343117],"iteration":410,"passed_time":5.779388206,"remaining_time":8.282383585},
{"learn":[0.4237211547],"iteration":411,"passed_time":5.792873264,"remaining_time":8.267498736},
{"learn":[0.423710273],"iteration":412,"passed_time":5.806468778,"remaining_time":8.252777658},
{"learn":[0.4236994941],"iteration":413,"passed_time":5.820834982,"remaining_time":8.239152898},
{"learn":[0.4236880346],"iteration":414,"passed_time":5.83490886,"remaining_time":8.225112489},
{"learn":[0.4236808591],"iteration":415,"passed_time":5.848138716,"remaining_time":8.209887043},
{"learn":[0.4236723221],"iteration":416,"passed_time":5.862184011,"remaining_time":8.195811219},
{"learn":[0.4236615019],"iteration":417,"passed_time":5.875365409,"remaining_time":8.180532699},
{"learn":[0.42365128],"iteration":418,"passed_time":5.889196418,"remaining_time":8.166164961},
{"learn":[0.423638349],"iteration":419,"passed_time":5.903747576,"remaining_time":8.152794271},
{"learn":[0.4236295378],"iteration":420,"passed_time":5.917435796,"remaining_time":8.138231178},
{"learn":[0.4236160295],"iteration":421,"passed_time":5.932663563,"remaining_time":8.125780899},
{"learn":[0.4236097632],"iteration":422,"passed_time":5.945043939,"remaining_time":8.109433458},
{"learn":[0.4235985999],"iteration":423,"passed_time":5.959612138,"remaining_time":8.096076867},
{"learn":[0.4235914001],"iteration":424,"passed_time":5.972728955,"remaining_time":8.080750939},
{"learn":[0.4235837295],"iteration":425,"passed_time":5.987213073,"remaining_time":8.067277709},
{"learn":[0.4235746021],"iteration":426,"passed_time":6.000774838,"remaining_time":8.052562019},
{"learn":[0.423567535],"iteration":427,"passed_time":6.013383041,"remaining_time":8.036577336},
{"learn":[0.4235590301],"iteration":428,"passed_time":6.027321922,"remaining_time":8.022379528},
{"learn":[0.4235446252],"iteration":429,"passed_time":6.043047469,"remaining_time":8.010551297},
{"learn":[0.4235345119],"iteration":430,"passed_time":6.057382258,"remaining_time":7.99686892},
{"learn":[0.4235264965],"iteration":431,"passed_time":6.070509033,"remaining_time":7.981595209},
{"learn":[0.4235195592],"iteration":432,"passed_time":6.085989127,"remaining_time":7.969413014},
{"learn":[0.4235096478],"iteration":433,"passed_time":6.102944895,"remaining_time":7.959140117},
{"learn":[0.4235012236],"iteration":434,"passed_time":6.116666531,"remaining_time":7.94463584},
{"learn":[0.4234944553],"iteration":435,"passed_time":6.129964927,"remaining_time":7.929587658},
{"learn":[0.4234882467],"iteration":436,"passed_time":6.142977746,"remaining_time":7.914179568},
{"learn":[0.4234788436],"iteration":437,"passed_time":6.156260851,"remaining_time":7.89912922},
{"learn":[0.4234714262],"iteration":438,"passed_time":6.170167483,"remaining_time":7.884883731},
{"learn":[0.4234650858],"iteration":439,"passed_time":6.183407172,"remaining_time":7.869790946},
{"learn":[0.4234556713],"iteration":440,"passed_time":6.198542983,"remaining_time":7.857110039},
{"learn":[0.4234504143],"iteration":441,"passed_time":6.212400907,"remaining_time":7.842804765},
{"learn":[0.4234456072],"iteration":442,"passed_time":6.225104358,"remaining_time":7.82704995},
{"learn":[0.4234332632],"iteration":443,"passed_time":6.239465438,"remaining_time":7.813384647},
{"learn":[0.4234265636],"iteration":444,"passed_time":6.253577648,"remaining_time":7.79940583},
{"learn":[0.4234169438],"iteration":445,"passed_time":6.267710774,"remaining_time":7.785452396},
{"learn":[0.4234080492],"iteration":446,"passed_time":6.282069853,"remaining_time":7.771777693},
{"learn":[0.4234024263],"iteration":447,"passed_time":6.295497871,"remaining_time":7.756952734},
{"learn":[0.4233962749],"iteration":448,"passed_time":6.308885765,"remaining_time":7.742084758},
{"learn":[0.4233874534],"iteration":449,"passed_time":6.321908709,"remaining_time":7.726777311},
{"learn":[0.423377214],"iteration":450,"passed_time":6.337021645,"remaining_time":7.714024132},
{"learn":[0.4233685622],"iteration":451,"passed_time":6.350269501,"remaining_time":7.698999306},
{"learn":[0.4233616676],"iteration":452,"passed_time":6.36441221,"remaining_time":7.685062868},
{"learn":[0.4233517881],"iteration":453,"passed_time":6.378781914,"remaining_time":7.671398514},
{"learn":[0.4233437435],"iteration":454,"passed_time":6.392339762,"remaining_time":7.656758616},
{"learn":[0.4233365624],"iteration":455,"passed_time":6.405255292,"remaining_time":7.641357191},
{"learn":[0.4233268912],"iteration":456,"passed_time":6.419389168,"remaining_time":7.627414264},
{"learn":[0.4233185709],"iteration":457,"passed_time":6.432480444,"remaining_time":7.612236683},
{"learn":[0.4233104207],"iteration":458,"passed_time":6.446214622,"remaining_time":7.597825948},
{"learn":[0.423301093],"iteration":459,"passed_time":6.459556975,"remaining_time":7.582958188},
{"learn":[0.4232933688],"iteration":460,"passed_time":6.472022973,"remaining_time":7.567072414},
{"learn":[0.4232877569],"iteration":461,"passed_time":6.484635885,"remaining_time":7.551372525},
{"learn":[0.4232806067],"iteration":462,"passed_time":6.496803391,"remaining_time":7.535169376},
{"learn":[0.4232744716],"iteration":463,"passed_time":6.509566966,"remaining_time":7.519672185},
{"learn":[0.423265912],"iteration":464,"passed_time":6.523023275,"remaining_time":7.504983768},
{"learn":[0.4232571114],"iteration":465,"passed_time":6.537711305,"remaining_time":7.491712096},
{"learn":[0.4232480639],"iteration":466,"passed_time":6.551539313,"remaining_time":7.477452792},
{"learn":[0.4232378664],"iteration":467,"passed_time":6.566621876,"remaining_time":7.464621448},
{"learn":[0.4232275572],"iteration":468,"passed_time":6.580868583,"remaining_time":7.450834152},
{"learn":[0.4232178494],"iteration":469,"passed_time":6.594860712,"remaining_time":7.436757824},
{"learn":[0.423212015],"iteration":470,"passed_time":6.608255106,"remaining_time":7.422010512},
{"learn":[0.4232027984],"iteration":471,"passed_time":6.622177695,"remaining_time":7.407859795},
{"learn":[0.4231972197],"iteration":472,"passed_time":6.634664777,"remaining_time":7.39211065},
{"learn":[0.4231927018],"iteration":473,"passed_time":6.647080819,"remaining_time":7.376296436},
{"learn":[0.4231845201],"iteration":474,"passed_time":6.661610519,"remaining_time":7.362832679},
{"learn":[0.4231711348],"iteration":475,"passed_time":6.677210236,"remaining_time":7.35054236},
{"learn":[0.4231581472],"iteration":476,"passed_time":6.693371439,"remaining_time":7.3388538},
{"learn":[0.423150901],"iteration":477,"passed_time":6.70633801,"remaining_time":7.323657826},
{"learn":[0.4231435449],"iteration":478,"passed_time":6.719768777,"remaining_time":7.308976061},
{"learn":[0.4231348741],"iteration":479,"passed_time":6.734093274,"remaining_time":7.295267714},
{"learn":[0.4231272508],"iteration":480,"passed_time":6.747622456,"remaining_time":7.280698659},
{"learn":[0.4231217747],"iteration":481,"passed_time":6.760623234,"remaining_time":7.265566048},
{"learn":[0.4231155472],"iteration":482,"passed_time":6.773510973,"remaining_time":7.250321269},
{"learn":[0.423107922],"iteration":483,"passed_time":6.786916158,"remaining_time":7.235637887},
{"learn":[0.4231014546],"iteration":484,"passed_time":6.799896395,"remaining_time":7.220508543},
{"learn":[0.4230943197],"iteration":485,"passed_time":6.812525973,"remaining_time":7.205017181},
{"learn":[0.4230895474],"iteration":486,"passed_time":6.825361338,"remaining_time":7.189754346},
{"learn":[0.4230775977],"iteration":487,"passed_time":6.839641086,"remaining_time":7.176016877},
{"learn":[0.4230714246],"iteration":488,"passed_time":6.853115686,"remaining_time":7.161435819},
{"learn":[0.4230601629],"iteration":489,"passed_time":6.868219914,"remaining_time":7.148555421},
{"learn":[0.4230534342],"iteration":490,"passed_time":6.882112755,"remaining_time":7.134410167},
{"learn":[0.423047647],"iteration":491,"passed_time":6.896164799,"remaining_time":7.120430321},
{"learn":[0.4230365296],"iteration":492,"passed_time":6.910300009,"remaining_time":7.106535709},
{"learn":[0.4230300665],"iteration":493,"passed_time":6.922927129,"remaining_time":7.091095399},
{"learn":[0.4230233013],"iteration":494,"passed_time":6.936367021,"remaining_time":7.076495648},
{"learn":[0.423018295],"iteration":495,"passed_time":6.951038385,"remaining_time":7.063151907},
{"learn":[0.423010963],"iteration":496,"passed_time":6.964690731,"remaining_time":7.048771504},
{"learn":[0.4230005817],"iteration":497,"passed_time":6.979795918,"remaining_time":7.035858536},
{"learn":[0.4229896575],"iteration":498,"passed_time":6.997745079,"remaining_time":7.025792154},
{"learn":[0.4229790033],"iteration":499,"passed_time":7.011971203,"remaining_time":7.011971203},
{"learn":[0.4229726092],"iteration":500,"passed_time":7.026127496,"remaining_time":6.998079083},
{"learn":[0.4229641368],"iteration":501,"passed_time":7.039589596,"remaining_time":6.983497249},
{"learn":[0.4229552289],"iteration":502,"passed_time":7.053978633,"remaining_time":6.969835747},
{"learn":[0.4229485956],"iteration":503,"passed_time":7.068109884,"remaining_time":6.955917664},
{"learn":[0.422940255],"iteration":504,"passed_time":7.081911727,"remaining_time":6.941675851},
{"learn":[0.4229336105],"iteration":505,"passed_time":7.095715652,"remaining_time":6.927437811},
{"learn":[0.4229238287],"iteration":506,"passed_time":7.110029941,"remaining_time":6.913697753},
{"learn":[0.422917735],"iteration":507,"passed_time":7.123700661,"remaining_time":6.899332137},
{"learn":[0.4229108753],"iteration":508,"passed_time":7.137533003,"remaining_time":6.885125156},
{"learn":[0.4229001727],"iteration":509,"passed_time":7.151950498,"remaining_time":6.871481851},
{"learn":[0.422893668],"iteration":510,"passed_time":7.165746465,"remaining_time":6.857240747},
{"learn":[0.4228856496],"iteration":511,"passed_time":7.180187959,"remaining_time":6.843616649},
{"learn":[0.4228807017],"iteration":512,"passed_time":7.192721665,"remaining_time":6.828178267},
{"learn":[0.4228762091],"iteration":513,"passed_time":7.205607195,"remaining_time":6.813083846},
{"learn":[0.4228687964],"iteration":514,"passed_time":7.219364872,"remaining_time":6.798819346},
{"learn":[0.422862316],"iteration":515,"passed_time":7.234346312,"remaining_time":6.78570468},
{"learn":[0.4228548947],"iteration":516,"passed_time":7.248855512,"remaining_time":6.77214161},
{"learn":[0.4228461021],"iteration":517,"passed_time":7.263610666,"remaining_time":6.758803747},
{"learn":[0.4228347581],"iteration":518,"passed_time":7.277879164,"remaining_time":6.745009398},
{"learn":[0.4228223113],"iteration":519,"passed_time":7.292810771,"remaining_time":6.731825327},
{"learn":[0.4228152104],"iteration":520,"passed_time":7.307505759,"remaining_time":6.718417003},
{"learn":[0.4228052839],"iteration":521,"passed_time":7.324187742,"remaining_time":6.706823258},
{"learn":[0.4227962098],"iteration":522,"passed_time":7.338246745,"remaining_time":6.692817777},
{"learn":[0.4227839888],"iteration":523,"passed_time":7.35380813,"remaining_time":6.680176851},
{"learn":[0.4227757277],"iteration":524,"passed_time":7.367501558,"remaining_time":6.665834743},
{"learn":[0.4227677174],"iteration":525,"passed_time":7.381342191,"remaining_time":6.651627754},
{"learn":[0.4227581845],"iteration":526,"passed_time":7.395490275,"remaining_time":6.637698103},
{"learn":[0.4227508996],"iteration":527,"passed_time":7.408020398,"remaining_time":6.622321265},
{"learn":[0.4227450292],"iteration":528,"passed_time":7.423961856,"remaining_time":6.609992504},
{"learn":[0.4227394143],"iteration":529,"passed_time":7.437405082,"remaining_time":6.595434696},
{"learn":[0.4227311841],"iteration":530,"passed_time":7.451503168,"remaining_time":6.581459483},
{"learn":[0.422725486],"iteration":531,"passed_time":7.464666358,"remaining_time":6.566661383},
{"learn":[0.4227153365],"iteration":532,"passed_time":7.478903732,"remaining_time":6.552810587},
{"learn":[0.4227112639],"iteration":533,"passed_time":7.491336815,"remaining_time":6.537383812},
{"learn":[0.4227005804],"iteration":534,"passed_time":7.505654854,"remaining_time":6.523606555},
{"learn":[0.4226912004],"iteration":535,"passed_time":7.520705708,"remaining_time":6.510461658},
{"learn":[0.4226856695],"iteration":536,"passed_time":7.533717403,"remaining_time":6.495551504},
{"learn":[0.4226797988],"iteration":537,"passed_time":7.546390147,"remaining_time":6.480357338},
{"learn":[0.4226692634],"iteration":538,"passed_time":7.560970596,"remaining_time":6.466804164},
{"learn":[0.4226611403],"iteration":539,"passed_time":7.575474338,"remaining_time":6.453181844},
{"learn":[0.4226509081],"iteration":540,"passed_time":7.589264556,"remaining_time":6.438950889},
{"learn":[0.4226429884],"iteration":541,"passed_time":7.603521387,"remaining_time":6.425115859},
{"learn":[0.4226369033],"iteration":542,"passed_time":7.618210667,"remaining_time":6.411643232},
{"learn":[0.4226303289],"iteration":543,"passed_time":7.631447231,"remaining_time":6.396948415},
{"learn":[0.4226230401],"iteration":544,"passed_time":7.644786751,"remaining_time":6.382344902},
{"learn":[0.4226147076],"iteration":545,"passed_time":7.658431056,"remaining_time":6.367999449},
{"learn":[0.4226088761],"iteration":546,"passed_time":7.67418631,"remaining_time":6.355404751},
{"learn":[0.4226016719],"iteration":547,"passed_time":7.687997736,"remaining_time":6.341195213},
{"learn":[0.422596827],"iteration":548,"passed_time":7.700044911,"remaining_time":6.325537805},
{"learn":[0.4225890775],"iteration":549,"passed_time":7.714953936,"remaining_time":6.312235038},
{"learn":[0.4225830863],"iteration":550,"passed_time":7.733475167,"remaining_time":6.301869964},
{"learn":[0.4225774824],"iteration":551,"passed_time":7.748024826,"remaining_time":6.288252032},
{"learn":[0.4225703281],"iteration":552,"passed_time":7.762315406,"remaining_time":6.274421314},
{"learn":[0.4225628441],"iteration":553,"passed_time":7.776374326,"remaining_time":6.260402436},
{"learn":[0.4225532741],"iteration":554,"passed_time":7.790993149,"remaining_time":6.246832345},
{"learn":[0.4225463436],"iteration":555,"passed_time":7.805183649,"remaining_time":6.232916439},
{"learn":[0.4225400497],"iteration":556,"passed_time":7.818484837,"remaining_time":6.218292249},
{"learn":[0.4225335303],"iteration":557,"passed_time":7.831686776,"remaining_time":6.203594185},
{"learn":[0.4225244669],"iteration":558,"passed_time":7.845622449,"remaining_time":6.189480322},
{"learn":[0.4225189529],"iteration":559,"passed_time":7.85877439,"remaining_time":6.174751306},
{"learn":[0.4225112398],"iteration":560,"passed_time":7.873340881,"remaining_time":6.161134843},
{"learn":[0.4225057958],"iteration":561,"passed_time":7.886133372,"remaining_time":6.146132415},
{"learn":[0.4224999789],"iteration":562,"passed_time":7.899367895,"remaining_time":6.131480941},
{"learn":[0.4224911649],"iteration":563,"passed_time":7.914441874,"remaining_time":6.118256484},
{"learn":[0.4224836022],"iteration":564,"passed_time":7.928226091,"remaining_time":6.104032478},
{"learn":[0.4224783622],"iteration":565,"passed_time":7.941458447,"remaining_time":6.089386866},
{"learn":[0.4224698653],"iteration":566,"passed_time":7.955428369,"remaining_time":6.075309495},
{"learn":[0.4224615726],"iteration":567,"passed_time":7.969104339,"remaining_time":6.061008934},
{"learn":[0.4224535105],"iteration":568,"passed_time":7.982673771,"remaining_time":6.046629868},
{"learn":[0.4224447828],"iteration":569,"passed_time":7.996657192,"remaining_time":6.032565952},
{"learn":[0.4224373053],"iteration":570,"passed_time":8.009893089,"remaining_time":6.017940692},
{"learn":[0.4224327757],"iteration":571,"passed_time":8.023746889,"remaining_time":6.003782637},
{"learn":[0.4224253796],"iteration":572,"passed_time":8.038387336,"remaining_time":5.990211855},
{"learn":[0.4224181876],"iteration":573,"passed_time":8.051962017,"remaining_time":5.975846375},
{"learn":[0.422412715],"iteration":574,"passed_time":8.065875899,"remaining_time":5.96173436},
{"learn":[0.4224045734],"iteration":575,"passed_time":8.080466306,"remaining_time":5.948121031},
{"learn":[0.4223958954],"iteration":576,"passed_time":8.093606664,"remaining_time":5.933441281},
{"learn":[0.4223883369],"iteration":577,"passed_time":8.10683602,"remaining_time":5.918831835},
{"learn":[0.4223796176],"iteration":578,"passed_time":8.120386326,"remaining_time":5.904460524},
{"learn":[0.4223704115],"iteration":579,"passed_time":8.133560934,"remaining_time":5.889819986},
{"learn":[0.4223627253],"iteration":580,"passed_time":8.147921054,"remaining_time":5.876039452},
{"learn":[0.4223551908],"iteration":581,"passed_time":8.161871768,"remaining_time":5.861962885},
{"learn":[0.4223492994],"iteration":582,"passed_time":8.175899064,"remaining_time":5.847941526},
{"learn":[0.42234302],"iteration":583,"passed_time":8.19054722,"remaining_time":5.834362403},
{"learn":[0.4223355741],"iteration":584,"passed_time":8.205289623,"remaining_time":5.820846485},
{"learn":[0.422329794],"iteration":585,"passed_time":8.218662059,"remaining_time":5.80635852},
{"learn":[0.4223233966],"iteration":586,"passed_time":8.231405968,"remaining_time":5.791432138},
{"learn":[0.4223182313],"iteration":587,"passed_time":8.244966899,"remaining_time":5.777085651},
{"learn":[0.4223111308],"iteration":588,"passed_time":8.259656096,"remaining_time":5.763529126},
{"learn":[0.4223068024],"iteration":589,"passed_time":8.272687081,"remaining_time":5.748816446},
{"learn":[0.4222995054],"iteration":590,"passed_time":8.287650896,"remaining_time":5.735447067},
{"learn":[0.4222928471],"iteration":591,"passed_time":8.301644818,"remaining_time":5.721403861},
{"learn":[0.4222875146],"iteration":592,"passed_time":8.315897649,"remaining_time":5.707538522},
{"learn":[0.4222787958],"iteration":593,"passed_time":8.33231593,"remaining_time":5.695151966},
{"learn":[0.4222707216],"iteration":594,"passed_time":8.345443663,"remaining_time":5.680512073},
{"learn":[0.4222647127],"iteration":595,"passed_time":8.359773285,"remaining_time":5.666691958},
{"learn":[0.4222587279],"iteration":596,"passed_time":8.373801872,"remaining_time":5.652666925},
{"learn":[0.4222533431],"iteration":597,"passed_time":8.386749651,"remaining_time":5.637915317},
{"learn":[0.4222464548],"iteration":598,"passed_time":8.40047237,"remaining_time":5.623688515},
{"learn":[0.422239807],"iteration":599,"passed_time":8.414090967,"remaining_time":5.609393978},
{"learn":[0.4222328795],"iteration":600,"passed_time":8.427332073,"remaining_time":5.594851077},
{"learn":[0.4222265189],"iteration":601,"passed_time":8.441489573,"remaining_time":5.580918356},
{"learn":[0.4222201721],"iteration":602,"passed_time":8.454428728,"remaining_time":5.566182761},
{"learn":[0.4222140976],"iteration":603,"passed_time":8.467899203,"remaining_time":5.551801464},
{"learn":[0.4222083037],"iteration":604,"passed_time":8.481675671,"remaining_time":5.537622959},
{"learn":[0.4222017856],"iteration":605,"passed_time":8.494949901,"remaining_time":5.523119242},
{"learn":[0.4221961257],"iteration":606,"passed_time":8.507853139,"remaining_time":5.50837938},
{"learn":[0.4221911007],"iteration":607,"passed_time":8.520789168,"remaining_time":5.493666701},
{"learn":[0.4221853011],"iteration":608,"passed_time":8.534666592,"remaining_time":5.479564265},
{"learn":[0.422174478],"iteration":609,"passed_time":8.549554451,"remaining_time":5.466108583},
{"learn":[0.422169148],"iteration":610,"passed_time":8.561601876,"remaining_time":5.45083982},
{"learn":[0.4221634423],"iteration":611,"passed_time":8.573915962,"remaining_time":5.435750642},
{"learn":[0.4221566412],"iteration":612,"passed_time":8.587744345,"remaining_time":5.421626528},
{"learn":[0.4221510889],"iteration":613,"passed_time":8.601031783,"remaining_time":5.407163303},
{"learn":[0.4221458695],"iteration":614,"passed_time":8.614134642,"remaining_time":5.392588353},
{"learn":[0.4221387894],"iteration":615,"passed_time":8.627928901,"remaining_time":5.378449185},
{"learn":[0.4221288744],"iteration":616,"passed_time":8.641919489,"remaining_time":5.364433005},
{"learn":[0.4221228808],"iteration":617,"passed_time":8.655562877,"remaining_time":5.350202296},
{"learn":[0.422115382],"iteration":618,"passed_time":8.671934325,"remaining_time":5.33765263},
{"learn":[0.4221057335],"iteration":619,"passed_time":8.687401212,"remaining_time":5.324536227},
{"learn":[0.4221005526],"iteration":620,"passed_time":8.700587361,"remaining_time":5.310020305},
{"learn":[0.4220913096],"iteration":621,"passed_time":8.716104163,"remaining_time":5.296925038},
{"learn":[0.4220859086],"iteration":622,"passed_time":8.729438016,"remaining_time":5.282501015},
{"learn":[0.4220783827],"iteration":623,"passed_time":8.743264858,"remaining_time":5.268377543},
{"learn":[0.4220707541],"iteration":624,"passed_time":8.75772631,"remaining_time":5.254635786},
{"learn":[0.4220616954],"iteration":625,"passed_time":8.77210293,"remaining_time":5.240841048},
{"learn":[0.4220578742],"iteration":626,"passed_time":8.785674903,"remaining_time":5.226565772},
{"learn":[0.422051125],"iteration":627,"passed_time":8.799478912,"remaining_time":5.212430184},
{"learn":[0.4220452143],"iteration":628,"passed_time":8.812618645,"remaining_time":5.197903843},
{"learn":[0.4220402948],"iteration":629,"passed_time":8.826763729,"remaining_time":5.183972349},
{"learn":[0.4220356311],"iteration":630,"passed_time":8.839222312,"remaining_time":5.169053935},
{"learn":[0.4220291054],"iteration":631,"passed_time":8.853673597,"remaining_time":5.155303613},
{"learn":[0.4220223942],"iteration":632,"passed_time":8.867099781,"remaining_time":5.140956745},
{"learn":[0.4220176547],"iteration":633,"passed_time":8.880514966,"remaining_time":5.126606432},
{"learn":[0.4220121959],"iteration":634,"passed_time":8.89452597,"remaining_time":5.112601542},
{"learn":[0.4220045875],"iteration":635,"passed_time":8.909018297,"remaining_time":5.098872107},
{"learn":[0.4219998406],"iteration":636,"passed_time":8.922529937,"remaining_time":5.084581424},
{"learn":[0.4219932715],"iteration":637,"passed_time":8.935363386,"remaining_time":5.069908379},
{"learn":[0.4219870525],"iteration":638,"passed_time":8.948427662,"remaining_time":5.055371496},
{"learn":[0.4219813335],"iteration":639,"passed_time":8.962317419,"remaining_time":5.041303548},
{"learn":[0.4219752038],"iteration":640,"passed_time":8.980047044,"remaining_time":5.029386722},
{"learn":[0.4219702084],"iteration":641,"passed_time":8.994000841,"remaining_time":5.015346264},
{"learn":[0.4219646964],"iteration":642,"passed_time":9.007009286,"remaining_time":5.000781205},
{"learn":[0.4219578291],"iteration":643,"passed_time":9.021134746,"remaining_time":4.986838462},
{"learn":[0.4219496443],"iteration":644,"passed_time":9.034455599,"remaining_time":4.972452307},
{"learn":[0.4219417247],"iteration":645,"passed_time":9.0482639,"remaining_time":4.958336564},
{"learn":[0.4219373217],"iteration":646,"passed_time":9.062252988,"remaining_time":4.944320409},
{"learn":[0.4219261104],"iteration":647,"passed_time":9.077242761,"remaining_time":4.930847919},
{"learn":[0.4219166745],"iteration":648,"passed_time":9.092578192,"remaining_time":4.917557697},
{"learn":[0.4219102175],"iteration":649,"passed_time":9.106667069,"remaining_time":4.90358996},
{"learn":[0.4219012523],"iteration":650,"passed_time":9.120791571,"remaining_time":4.88964095},
{"learn":[0.4218941278],"iteration":651,"passed_time":9.13393197,"remaining_time":4.875166144},
{"learn":[0.4218867474],"iteration":652,"passed_time":9.14704512,"remaining_time":4.860680945},
{"learn":[0.4218792869],"iteration":653,"passed_time":9.16131841,"remaining_time":4.846813715},
{"learn":[0.4218709897],"iteration":654,"passed_time":9.176335641,"remaining_time":4.833337093},
{"learn":[0.4218639901],"iteration":655,"passed_time":9.190384519,"remaining_time":4.819347979},
{"learn":[0.4218586339],"iteration":656,"passed_time":9.203844661,"remaining_time":4.805051322},
{"learn":[0.4218510377],"iteration":657,"passed_time":9.217189847,"remaining_time":4.790697459},
{"learn":[0.42184547],"iteration":658,"passed_time":9.230857193,"remaining_time":4.776513358},
{"learn":[0.4218405411],"iteration":659,"passed_time":9.243864637,"remaining_time":4.761990874},
{"learn":[0.4218327497],"iteration":660,"passed_time":9.257689646,"remaining_time":4.747892269},
{"learn":[0.4218267458],"iteration":661,"passed_time":9.270905544,"remaining_time":4.733483495},
{"learn":[0.4218213355],"iteration":662,"passed_time":9.283465207,"remaining_time":4.718744758},
{"learn":[0.4218144442],"iteration":663,"passed_time":9.297248841,"remaining_time":4.704631944},
{"learn":[0.4218074425],"iteration":664,"passed_time":9.311766084,"remaining_time":4.690889681},
{"learn":[0.4218012055],"iteration":665,"passed_time":9.325342181,"remaining_time":4.676673106},
{"learn":[0.4217945666],"iteration":666,"passed_time":9.338743491,"remaining_time":4.662371188},
{"learn":[0.4217867894],"iteration":667,"passed_time":9.352454044,"remaining_time":4.648225663},
{"learn":[0.4217801868],"iteration":668,"passed_time":9.365648859,"remaining_time":4.633826267},
{"learn":[0.4217730117],"iteration":669,"passed_time":9.380001355,"remaining_time":4.620000668},
{"learn":[0.4217667755],"iteration":670,"passed_time":9.392950218,"remaining_time":4.605485278},
{"learn":[0.4217588349],"iteration":671,"passed_time":9.407058844,"remaining_time":4.591540626},
{"learn":[0.4217520992],"iteration":672,"passed_time":9.421496672,"remaining_time":4.577755441},
{"learn":[0.4217454156],"iteration":673,"passed_time":9.435176267,"remaining_time":4.563601577},
{"learn":[0.4217379812],"iteration":674,"passed_time":9.449511264,"remaining_time":4.549764683},
{"learn":[0.4217316071],"iteration":675,"passed_time":9.463643223,"remaining_time":4.535829001},
{"learn":[0.4217233317],"iteration":676,"passed_time":9.478319962,"remaining_time":4.522152655},
{"learn":[0.4217160387],"iteration":677,"passed_time":9.491351114,"remaining_time":4.507691827},
{"learn":[0.4217120203],"iteration":678,"passed_time":9.503844404,"remaining_time":4.492980933},
{"learn":[0.4217083531],"iteration":679,"passed_time":9.516911888,"remaining_time":4.478546771},
{"learn":[0.4217020417],"iteration":680,"passed_time":9.531112971,"remaining_time":4.464647633},
{"learn":[0.4216965602],"iteration":681,"passed_time":9.544079792,"remaining_time":4.450172102},
{"learn":[0.4216895883],"iteration":682,"passed_time":9.55807513,"remaining_time":4.436178354},
{"learn":[0.4216844821],"iteration":683,"passed_time":9.571194405,"remaining_time":4.421779871},
{"learn":[0.4216798081],"iteration":684,"passed_time":9.584622214,"remaining_time":4.407527004},
{"learn":[0.4216736539],"iteration":685,"passed_time":9.597725031,"remaining_time":4.393127784},
{"learn":[0.4216687069],"iteration":686,"passed_time":9.611833325,"remaining_time":4.379190438},
{"learn":[0.421661914],"iteration":687,"passed_time":9.625750748,"remaining_time":4.365166037},
{"learn":[0.4216567202],"iteration":688,"passed_time":9.638605321,"remaining_time":4.350662198},
{"learn":[0.421651015],"iteration":689,"passed_time":9.651309231,"remaining_time":4.336095451},
{"learn":[0.4216463661],"iteration":690,"passed_time":9.665528438,"remaining_time":4.322211704},
{"learn":[0.4216395106],"iteration":691,"passed_time":9.679122577,"remaining_time":4.308048777},
{"learn":[0.4216333318],"iteration":692,"passed_time":9.693334951,"remaining_time":4.294161371},
{"learn":[0.4216272202],"iteration":693,"passed_time":9.708403222,"remaining_time":4.280650412},
{"learn":[0.4216217602],"iteration":694,"passed_time":9.721514289,"remaining_time":4.266276055},
{"learn":[0.421616453],"iteration":695,"passed_time":9.734399612,"remaining_time":4.251806727},
{"learn":[0.4216085357],"iteration":696,"passed_time":9.747771089,"remaining_time":4.237553285},
{"learn":[0.4216026044],"iteration":697,"passed_time":9.76220025,"remaining_time":4.223759994},
{"learn":[0.4215965549],"iteration":698,"passed_time":9.776286877,"remaining_time":4.209817382},
{"learn":[0.4215883595],"iteration":699,"passed_time":9.790401171,"remaining_time":4.195886216},
{"learn":[0.4215812225],"iteration":700,"passed_time":9.804659211,"remaining_time":4.18201584},
{"learn":[0.4215767574],"iteration":701,"passed_time":9.817381078,"remaining_time":4.167492253},
{"learn":[0.4215708946],"iteration":702,"passed_time":9.831122256,"remaining_time":4.153404424},
{"learn":[0.4215638506],"iteration":703,"passed_time":9.846181527,"remaining_time":4.139871778},
{"learn":[0.4215581646],"iteration":704,"passed_time":9.85995412,"remaining_time":4.125796405},
{"learn":[0.4215527188],"iteration":705,"passed_time":9.873701005,"remaining_time":4.111711183},
{"learn":[0.4215442838],"iteration":706,"passed_time":9.887552805,"remaining_time":4.097670399},
{"learn":[0.4215359541],"iteration":707,"passed_time":9.902078047,"remaining_time":4.083907895},
{"learn":[0.4215277368],"iteration":708,"passed_time":9.916816242,"remaining_time":4.070230644},
{"learn":[0.4215223097],"iteration":709,"passed_time":9.929535152,"remaining_time":4.055725625},
{"learn":[0.4215159319],"iteration":710,"passed_time":9.943907522,"remaining_time":4.041897713},
{"learn":[0.4215113242],"iteration":711,"passed_time":9.956859426,"remaining_time":4.0274937},
{"learn":[0.421503616],"iteration":712,"passed_time":9.971321295,"remaining_time":4.013701559},
{"learn":[0.4214973192],"iteration":713,"passed_time":9.985219843,"remaining_time":3.999681898},
{"learn":[0.4214920856],"iteration":714,"passed_time":9.997983668,"remaining_time":3.985210273},
{"learn":[0.4214871689],"iteration":715,"passed_time":10.01149502,"remaining_time":3.971039923},
{"learn":[0.4214813771],"iteration":716,"passed_time":10.02458771,"remaining_time":3.956706167},
{"learn":[0.4214714139],"iteration":717,"passed_time":10.03835876,"remaining_time":3.942642299},
{"learn":[0.4214641407],"iteration":718,"passed_time":10.05222181,"remaining_time":3.9286152},
{"learn":[0.4214562105],"iteration":719,"passed_time":10.06639302,"remaining_time":3.914708396},
{"learn":[0.4214505799],"iteration":720,"passed_time":10.0794143,"remaining_time":3.900355879},
{"learn":[0.4214454276],"iteration":721,"passed_time":10.09223979,"remaining_time":3.885931663},
{"learn":[0.4214408703],"iteration":722,"passed_time":10.10539164,"remaining_time":3.871636909},
{"learn":[0.42143649],"iteration":723,"passed_time":10.11968698,"remaining_time":3.857781223},
{"learn":[0.4214324437],"iteration":724,"passed_time":10.13222739,"remaining_time":3.843258665},
{"learn":[0.4214258657],"iteration":725,"passed_time":10.14529367,"remaining_time":3.828940034},
{"learn":[0.4214194987],"iteration":726,"passed_time":10.15858681,"remaining_time":3.814710041},
{"learn":[0.4214143378],"iteration":727,"passed_time":10.17162105,"remaining_time":3.800385886},
{"learn":[0.4214091541],"iteration":728,"passed_time":10.18521323,"remaining_time":3.786272681},
{"learn":[0.4214008451],"iteration":729,"passed_time":10.19877595,"remaining_time":3.772150009},
{"learn":[0.4213929438],"iteration":730,"passed_time":10.21315136,"remaining_time":3.75832793},
{"learn":[0.4213866772],"iteration":731,"passed_time":10.22764748,"remaining_time":3.744548531},
{"learn":[0.4213814011],"iteration":732,"passed_time":10.24172252,"remaining_time":3.730613798},
{"learn":[0.4213747217],"iteration":733,"passed_time":10.25588003,"remaining_time":3.716708565},
{"learn":[0.4213698072],"iteration":734,"passed_time":10.2692965,"remaining_time":3.702535473},
{"learn":[0.4213645864],"iteration":735,"passed_time":10.28243257,"remaining_time":3.688263856},
{"learn":[0.4213590776],"iteration":736,"passed_time":10.29528602,"remaining_time":3.673894467},
{"learn":[0.4213544571],"iteration":737,"passed_time":10.30878557,"remaining_time":3.659758564},
{"learn":[0.4213496952],"iteration":738,"passed_time":10.32142144,"remaining_time":3.645319346},
{"learn":[0.4213438392],"iteration":739,"passed_time":10.33378653,"remaining_time":3.630789861},
{"learn":[0.4213380067],"iteration":740,"passed_time":10.34882563,"remaining_time":3.617200862},
{"learn":[0.4213329619],"iteration":741,"passed_time":10.3614405,"remaining_time":3.602765027},
{"learn":[0.421324596],"iteration":742,"passed_time":10.37566475,"remaining_time":3.588890769},
{"learn":[0.4213171599],"iteration":743,"passed_time":10.38911619,"remaining_time":3.574749656},
{"learn":[0.4213110017],"iteration":744,"passed_time":10.40233954,"remaining_time":3.560532327},
{"learn":[0.4213051049],"iteration":745,"passed_time":10.41584993,"remaining_time":3.546415393},
{"learn":[0.421299601],"iteration":746,"passed_time":10.42864784,"remaining_time":3.532058773},
{"learn":[0.4212923469],"iteration":747,"passed_time":10.44327591,"remaining_time":3.518322901},
{"learn":[0.4212867382],"iteration":748,"passed_time":10.457492,"remaining_time":3.504446584},
{"learn":[0.4212776584],"iteration":749,"passed_time":10.47194324,"remaining_time":3.490647747},
{"learn":[0.4212722672],"iteration":750,"passed_time":10.485552,"remaining_time":3.476567842},
{"learn":[0.4212679999],"iteration":751,"passed_time":10.4982135,"remaining_time":3.462176792},
{"learn":[0.4212609798],"iteration":752,"passed_time":10.51158873,"remaining_time":3.448024456},
{"learn":[0.4212556071],"iteration":753,"passed_time":10.52525278,"remaining_time":3.433968413},
{"learn":[0.4212508536],"iteration":754,"passed_time":10.53817793,"remaining_time":3.419673634},
{"learn":[0.4212450159],"iteration":755,"passed_time":10.55169982,"remaining_time":3.405575076},
{"learn":[0.4212392884],"iteration":756,"passed_time":10.56527776,"remaining_time":3.39149603},
{"learn":[0.4212349598],"iteration":757,"passed_time":10.57900756,"remaining_time":3.377466793},
{"learn":[0.421227605],"iteration":758,"passed_time":10.59469194,"remaining_time":3.364058969},
{"learn":[0.421219514],"iteration":759,"passed_time":10.60889219,"remaining_time":3.350176481},
{"learn":[0.4212126006],"iteration":760,"passed_time":10.62193176,"remaining_time":3.335928634},
{"learn":[0.4212083434],"iteration":761,"passed_time":10.63548552,"remaining_time":3.32184456},
{"learn":[0.4212036282],"iteration":762,"passed_time":10.64931674,"remaining_time":3.307848057},
{"learn":[0.4211963985],"iteration":763,"passed_time":10.66422643,"remaining_time":3.294185128},
{"learn":[0.4211927122],"iteration":764,"passed_time":10.67666497,"remaining_time":3.279759828},
{"learn":[0.421186899],"iteration":765,"passed_time":10.69107259,"remaining_time":3.265941236},
{"learn":[0.4211810593],"iteration":766,"passed_time":10.70677239,"remaining_time":3.252513646},
{"learn":[0.4211753096],"iteration":767,"passed_time":10.71951259,"remaining_time":3.238186095},
{"learn":[0.4211678605],"iteration":768,"passed_time":10.7340945,"remaining_time":3.224415902},
{"learn":[0.4211632476],"iteration":769,"passed_time":10.74792067,"remaining_time":3.210417863},
{"learn":[0.4211576004],"iteration":770,"passed_time":10.76180726,"remaining_time":3.196438214},
{"learn":[0.4211530537],"iteration":771,"passed_time":10.77492462,"remaining_time":3.182231624},
{"learn":[0.4211467827],"iteration":772,"passed_time":10.78850914,"remaining_time":3.168165037},
{"learn":[0.4211415636],"iteration":773,"passed_time":10.80315408,"remaining_time":3.154409332},
{"learn":[0.421136759],"iteration":774,"passed_time":10.8164074,"remaining_time":3.140247309},
{"learn":[0.4211317553],"iteration":775,"passed_time":10.82909664,"remaining_time":3.125924803},
{"learn":[0.4211270907],"iteration":776,"passed_time":10.84180505,"remaining_time":3.111612003},
{"learn":[0.4211188052],"iteration":777,"passed_time":10.85589822,"remaining_time":3.097698463},
{"learn":[0.4211136754],"iteration":778,"passed_time":10.86923857,"remaining_time":3.083570891},
{"learn":[0.4211068871],"iteration":779,"passed_time":10.88343549,"remaining_time":3.069686933},
{"learn":[0.4211010273],"iteration":780,"passed_time":10.89812939,"remaining_time":3.055941533},
{"learn":[0.4210964355],"iteration":781,"passed_time":10.91166099,"remaining_time":3.041869688},
{"learn":[0.421091317],"iteration":782,"passed_time":10.92514976,"remaining_time":3.027787353},
{"learn":[0.4210872403],"iteration":783,"passed_time":10.93747772,"remaining_time":3.013386718},
{"learn":[0.4210808164],"iteration":784,"passed_time":10.95145564,"remaining_time":2.999443265},
{"learn":[0.4210734587],"iteration":785,"passed_time":10.96588838,"remaining_time":2.985623555},
{"learn":[0.4210662359],"iteration":786,"passed_time":10.97967477,"remaining_time":2.971627352},
{"learn":[0.4210596832],"iteration":787,"passed_time":10.99336595,"remaining_time":2.957606067},
{"learn":[0.4210531735],"iteration":788,"passed_time":11.00804181,"remaining_time":2.943848951},
{"learn":[0.4210486717],"iteration":789,"passed_time":11.0210873,"remaining_time":2.929656117},
{"learn":[0.4210428293],"iteration":790,"passed_time":11.03548796,"remaining_time":2.915824252},
{"learn":[0.421036274],"iteration":791,"passed_time":11.04998958,"remaining_time":2.902017464},
{"learn":[0.4210312768],"iteration":792,"passed_time":11.06270744,"remaining_time":2.887743305},
{"learn":[0.421023231],"iteration":793,"passed_time":11.07651395,"remaining_time":2.873755509},
{"learn":[0.4210147009],"iteration":794,"passed_time":11.09078628,"remaining_time":2.859888287},
{"learn":[0.4210103195],"iteration":795,"passed_time":11.1040733,"remaining_time":2.84576753},
{"learn":[0.4210051802],"iteration":796,"passed_time":11.11668726,"remaining_time":2.831477432},
{"learn":[0.4209970548],"iteration":797,"passed_time":11.13053135,"remaining_time":2.817502923},
{"learn":[0.4209903497],"iteration":798,"passed_time":11.14372083,"remaining_time":2.803364064},
{"learn":[0.4209858037],"iteration":799,"passed_time":11.15843286,"remaining_time":2.789608215},
{"learn":[0.420978049],"iteration":800,"passed_time":11.17172388,"remaining_time":2.775496944},
{"learn":[0.4209716003],"iteration":801,"passed_time":11.18491203,"remaining_time":2.761362322},
{"learn":[0.4209667673],"iteration":802,"passed_time":11.19796131,"remaining_time":2.747195987},
{"learn":[0.4209626484],"iteration":803,"passed_time":11.21182252,"remaining_time":2.733230366},
{"learn":[0.4209563577],"iteration":804,"passed_time":11.22481213,"remaining_time":2.719053871},
{"learn":[0.4209507198],"iteration":805,"passed_time":11.23798057,"remaining_time":2.704923364},
{"learn":[0.4209445279],"iteration":806,"passed_time":11.25119126,"remaining_time":2.690805346},
{"learn":[0.4209385461],"iteration":807,"passed_time":11.26432108,"remaining_time":2.676670356},
{"learn":[0.4209328745],"iteration":808,"passed_time":11.27739861,"remaining_time":2.662525505},
{"learn":[0.4209269074],"iteration":809,"passed_time":11.29211743,"remaining_time":2.648768286},
{"learn":[0.4209199691],"iteration":810,"passed_time":11.30681504,"remaining_time":2.635003752},
{"learn":[0.4209151574],"iteration":811,"passed_time":11.32000281,"remaining_time":2.620887351},
{"learn":[0.420908181],"iteration":812,"passed_time":11.3329178,"remaining_time":2.606710491},
{"learn":[0.4208998469],"iteration":813,"passed_time":11.34678073,"remaining_time":2.592753336},
{"learn":[0.4208958042],"iteration":814,"passed_time":11.3597073,"remaining_time":2.578583865},
{"learn":[0.4208914237],"iteration":815,"passed_time":11.37315648,"remaining_time":2.564535285},
{"learn":[0.4208855845],"iteration":816,"passed_time":11.38774431,"remaining_time":2.550743217},
{"learn":[0.4208805284],"iteration":817,"passed_time":11.40108933,"remaining_time":2.536672686},
{"learn":[0.4208751377],"iteration":818,"passed_time":11.4152002,"remaining_time":2.522773183},
{"learn":[0.420869427],"iteration":819,"passed_time":11.42941233,"remaining_time":2.508895389},
{"learn":[0.4208624493],"iteration":820,"passed_time":11.44347583,"remaining_time":2.494984377},
{"learn":[0.420855452],"iteration":821,"passed_time":11.45763271,"remaining_time":2.481093214},
{"learn":[0.4208492382],"iteration":822,"passed_time":11.47132509,"remaining_time":2.467101508},
{"learn":[0.4208452092],"iteration":823,"passed_time":11.48386505,"remaining_time":2.452864379},
{"learn":[0.4208392547],"iteration":824,"passed_time":11.49824308,"remaining_time":2.43902126},
{"learn":[0.4208332605],"iteration":825,"passed_time":11.51154761,"remaining_time":2.424950706},
{"learn":[0.4208279813],"iteration":826,"passed_time":11.5254162,"remaining_time":2.411000002},
{"learn":[0.4208226318],"iteration":827,"passed_time":11.53884726,"remaining_time":2.396958609},
{"learn":[0.4208180498],"iteration":828,"passed_time":11.55263368,"remaining_time":2.38299199},
{"learn":[0.4208130002],"iteration":829,"passed_time":11.56588679,"remaining_time":2.368916571},
{"learn":[0.4208085382],"iteration":830,"passed_time":11.57958855,"remaining_time":2.354934374},
{"learn":[0.4208017264],"iteration":831,"passed_time":11.59435303,"remaining_time":2.34116744},
{"learn":[0.4207969652],"iteration":832,"passed_time":11.60836554,"remaining_time":2.327247353},
{"learn":[0.4207900511],"iteration":833,"passed_time":11.62254262,"remaining_time":2.313359803},
{"learn":[0.4207843859],"iteration":834,"passed_time":11.63548194,"remaining_time":2.299226971},
{"learn":[0.4207785864],"iteration":835,"passed_time":11.65007727,"remaining_time":2.285421856},
{"learn":[0.4207702359],"iteration":836,"passed_time":11.66476846,"remaining_time":2.271633524},
{"learn":[0.4207636502],"iteration":837,"passed_time":11.68187544,"remaining_time":2.258310049},
{"learn":[0.4207595731],"iteration":838,"passed_time":11.6943881,"remaining_time":2.244095929},
{"learn":[0.4207544468],"iteration":839,"passed_time":11.7077455,"remaining_time":2.230046761},
{"learn":[0.4207465058],"iteration":840,"passed_time":11.72319442,"remaining_time":2.216394665},
{"learn":[0.4207423139],"iteration":841,"passed_time":11.73676319,"remaining_time":2.202385491},
{"learn":[0.4207363071],"iteration":842,"passed_time":11.75045466,"remaining_time":2.188400215},
{"learn":[0.4207319534],"iteration":843,"passed_time":11.76299557,"remaining_time":2.174202973},
{"learn":[0.4207253521],"iteration":844,"passed_time":11.77726603,"remaining_time":2.160326905},
{"learn":[0.4207198426],"iteration":845,"passed_time":11.79147069,"remaining_time":2.146437928},
{"learn":[0.4207158912],"iteration":846,"passed_time":11.80507779,"remaining_time":2.132440262},
{"learn":[0.4207105977],"iteration":847,"passed_time":11.81844406,"remaining_time":2.118400351},
{"learn":[0.4207045655],"iteration":848,"passed_time":11.83157859,"remaining_time":2.104320809},
{"learn":[0.4206989264],"iteration":849,"passed_time":11.8461682,"remaining_time":2.090500271},
{"learn":[0.4206927213],"iteration":850,"passed_time":11.86000258,"remaining_time":2.076545693},
{"learn":[0.4206858708],"iteration":851,"passed_time":11.87448066,"remaining_time":2.062703213},
{"learn":[0.4206815559],"iteration":852,"passed_time":11.8890359,"remaining_time":2.048872541},
{"learn":[0.4206733998],"iteration":853,"passed_time":11.90297103,"remaining_time":2.034934158},
{"learn":[0.4206646139],"iteration":854,"passed_time":11.91895741,"remaining_time":2.021343654},
{"learn":[0.4206595221],"iteration":855,"passed_time":11.93338365,"remaining_time":2.0074851},
{"learn":[0.4206503592],"iteration":856,"passed_time":11.94785948,"remaining_time":1.993633495},
{"learn":[0.4206463574],"iteration":857,"passed_time":11.96197552,"remaining_time":1.979720891},
{"learn":[0.4206391773],"iteration":858,"passed_time":11.97657805,"remaining_time":1.965887667},
{"learn":[0.4206349502],"iteration":859,"passed_time":11.99103871,"remaining_time":1.952029558},
{"learn":[0.4206288099],"iteration":860,"passed_time":12.00529638,"remaining_time":1.938137278},
{"learn":[0.4206215977],"iteration":861,"passed_time":12.02021232,"remaining_time":1.924349536},
{"learn":[0.4206159425],"iteration":862,"passed_time":12.0336523,"remaining_time":1.910324872},
{"learn":[0.4206087261],"iteration":863,"passed_time":12.0482102,"remaining_time":1.896477532},
{"learn":[0.4206038651],"iteration":864,"passed_time":12.06086074,"remaining_time":1.882330867},
{"learn":[0.4205976417],"iteration":865,"passed_time":12.07479579,"remaining_time":1.868386415},
{"learn":[0.4205939585],"iteration":866,"passed_time":12.08864955,"remaining_time":1.854429515},
{"learn":[0.420587298],"iteration":867,"passed_time":12.10287625,"remaining_time":1.840529568},
{"learn":[0.4205827717],"iteration":868,"passed_time":12.11505193,"remaining_time":1.82631968},
{"learn":[0.4205753592],"iteration":869,"passed_time":12.1279495,"remaining_time":1.812222339},
{"learn":[0.4205711862],"iteration":870,"passed_time":12.14175496,"remaining_time":1.798262216},
{"learn":[0.4205638715],"iteration":871,"passed_time":12.15605788,"remaining_time":1.784375468},
{"learn":[0.4205568845],"iteration":872,"passed_time":12.17001197,"remaining_time":1.770437022},
{"learn":[0.4205501502],"iteration":873,"passed_time":12.18308824,"remaining_time":1.756371989},
{"learn":[0.4205436552],"iteration":874,"passed_time":12.1981056,"remaining_time":1.742586514},
{"learn":[0.4205372458],"iteration":875,"passed_time":12.21327424,"remaining_time":1.728819642},
{"learn":[0.420531973],"iteration":876,"passed_time":12.22637414,"remaining_time":1.714759429},
{"learn":[0.4205254418],"iteration":877,"passed_time":12.23991162,"remaining_time":1.700762206},
{"learn":[0.4205211815],"iteration":878,"passed_time":12.25272282,"remaining_time":1.686666053},
{"learn":[0.4205137015],"iteration":879,"passed_time":12.26775821,"remaining_time":1.67287612},
{"learn":[0.4205080725],"iteration":880,"passed_time":12.28277386,"remaining_time":1.659080692},
{"learn":[0.4205035894],"iteration":881,"passed_time":12.29632371,"remaining_time":1.645086392},
{"learn":[0.4204974403],"iteration":882,"passed_time":12.30933119,"remaining_time":1.631021234},
{"learn":[0.4204913325],"iteration":883,"passed_time":12.32287479,"remaining_time":1.617028819},
{"learn":[0.4204864136],"iteration":884,"passed_time":12.33568391,"remaining_time":1.602941977},
{"learn":[0.4204804402],"iteration":885,"passed_time":12.34912555,"remaining_time":1.588939405},
{"learn":[0.4204758555],"iteration":886,"passed_time":12.36254182,"remaining_time":1.574934865},
{"learn":[0.4204702002],"iteration":887,"passed_time":12.37682182,"remaining_time":1.561040589},
{"learn":[0.4204656633],"iteration":888,"passed_time":12.39046712,"remaining_time":1.547066198},
{"learn":[0.4204608556],"iteration":889,"passed_time":12.4034799,"remaining_time":1.533014369},
{"learn":[0.420454867],"iteration":890,"passed_time":12.41698933,"remaining_time":1.519025631},
{"learn":[0.4204485779],"iteration":891,"passed_time":12.43092338,"remaining_time":1.505089378},
{"learn":[0.4204414326],"iteration":892,"passed_time":12.4447258,"remaining_time":1.491137358},
{"learn":[0.4204360005],"iteration":893,"passed_time":12.45986537,"remaining_time":1.477344216},
{"learn":[0.4204318401],"iteration":894,"passed_time":12.4727476,"remaining_time":1.463283238},
{"learn":[0.4204251796],"iteration":895,"passed_time":12.48653457,"remaining_time":1.449329906},
{"learn":[0.4204182127],"iteration":896,"passed_time":12.49946135,"remaining_time":1.435278171},
{"learn":[0.4204131015],"iteration":897,"passed_time":12.51263471,"remaining_time":1.421256949},
{"learn":[0.4204084852],"iteration":898,"passed_time":12.52614772,"remaining_time":1.407275773},
{"learn":[0.4204033821],"iteration":899,"passed_time":12.54018189,"remaining_time":1.393353544},
{"learn":[0.420398763],"iteration":900,"passed_time":12.55537037,"remaining_time":1.379557899},
{"learn":[0.4203948053],"iteration":901,"passed_time":12.56999986,"remaining_time":1.365698433},
{"learn":[0.4203883984],"iteration":902,"passed_time":12.5849553,"remaining_time":1.351872275},
{"learn":[0.4203841122],"iteration":903,"passed_time":12.59846373,"remaining_time":1.337889954},
{"learn":[0.4203789476],"iteration":904,"passed_time":12.61209,"remaining_time":1.323921049},
{"learn":[0.4203733306],"iteration":905,"passed_time":12.62593596,"remaining_time":1.309975696},
{"learn":[0.420369245],"iteration":906,"passed_time":12.63862837,"remaining_time":1.295912281},
{"learn":[0.4203622972],"iteration":907,"passed_time":12.65487532,"remaining_time":1.282212037},
{"learn":[0.4203551703],"iteration":908,"passed_time":12.66904791,"remaining_time":1.268298525},
{"learn":[0.420349648],"iteration":909,"passed_time":12.68287363,"remaining_time":1.254350139},
{"learn":[0.4203429818],"iteration":910,"passed_time":12.69673838,"remaining_time":1.240405835},
{"learn":[0.4203353928],"iteration":911,"passed_time":12.7118859,"remaining_time":1.226585482},
{"learn":[0.4203301438],"iteration":912,"passed_time":12.72550904,"remaining_time":1.212616962},
{"learn":[0.4203250228],"iteration":913,"passed_time":12.73884585,"remaining_time":1.198622257},
{"learn":[0.4203182964],"iteration":914,"passed_time":12.75244432,"remaining_time":1.184653298},
{"learn":[0.4203121009],"iteration":915,"passed_time":12.76608467,"remaining_time":1.170688987},
{"learn":[0.4203057366],"iteration":916,"passed_time":12.77912032,"remaining_time":1.156670651},
{"learn":[0.420300539],"iteration":917,"passed_time":12.79219247,"remaining_time":1.142657715},
{"learn":[0.4202936535],"iteration":918,"passed_time":12.80592578,"remaining_time":1.128705101},
{"learn":[0.4202888253],"iteration":919,"passed_time":12.81934117,"remaining_time":1.114725319},
{"learn":[0.4202844154],"iteration":920,"passed_time":12.83249182,"remaining_time":1.100724054},
{"learn":[0.4202786721],"iteration":921,"passed_time":12.84567538,"remaining_time":1.086727419},
{"learn":[0.4202732973],"iteration":922,"passed_time":12.86003121,"remaining_time":1.07283034},
{"learn":[0.4202674272],"iteration":923,"passed_time":12.87401655,"remaining_time":1.058901794},
{"learn":[0.4202635843],"iteration":924,"passed_time":12.88653217,"remaining_time":1.04485396},
{"learn":[0.4202583806],"iteration":925,"passed_time":12.89948937,"remaining_time":1.030844723},
{"learn":[0.4202521574],"iteration":926,"passed_time":12.91305568,"remaining_time":1.016885722},
{"learn":[0.4202482632],"iteration":927,"passed_time":12.92807728,"remaining_time":1.003040479},
{"learn":[0.4202411563],"iteration":928,"passed_time":12.94215357,"remaining_time":0.9891204562},
{"learn":[0.4202353476],"iteration":929,"passed_time":12.95656003,"remaining_time":0.9752249483},
{"learn":[0.4202287221],"iteration":930,"passed_time":12.96993926,"remaining_time":0.9612522112},
{"learn":[0.420222103],"iteration":931,"passed_time":12.98351798,"remaining_time":0.9472953031},
{"learn":[0.42021791],"iteration":932,"passed_time":12.99702766,"remaining_time":0.9333342479},
{"learn":[0.420210697],"iteration":933,"passed_time":13.0121771,"remaining_time":0.9194900303},
{"learn":[0.4202048406],"iteration":934,"passed_time":13.02417773,"remaining_time":0.9054241203},
{"learn":[0.4201974747],"iteration":935,"passed_time":13.03825228,"remaining_time":0.8915044291},
{"learn":[0.4201924166],"iteration":936,"passed_time":13.05171163,"remaining_time":0.8775430442},
{"learn":[0.420188058],"iteration":937,"passed_time":13.06465332,"remaining_time":0.8635485138},
{"learn":[0.4201819778],"iteration":938,"passed_time":13.07794568,"remaining_time":0.8495790056},
{"learn":[0.4201768944],"iteration":939,"passed_time":13.09202997,"remaining_time":0.8356614874},
{"learn":[0.4201727499],"iteration":940,"passed_time":13.10508704,"remaining_time":0.8216792085},
{"learn":[0.4201667991],"iteration":941,"passed_time":13.11849901,"remaining_time":0.8077207461},
{"learn":[0.4201587689],"iteration":942,"passed_time":13.13331167,"remaining_time":0.7938481071},
{"learn":[0.4201541394],"iteration":943,"passed_time":13.14694526,"remaining_time":0.7799035325},
{"learn":[0.4201494452],"iteration":944,"passed_time":13.16145792,"remaining_time":0.7660107785},
{"learn":[0.4201446688],"iteration":945,"passed_time":13.17569946,"remaining_time":0.7521012378},
{"learn":[0.4201392241],"iteration":946,"passed_time":13.18981951,"remaining_time":0.7381841962},
{"learn":[0.420132108],"iteration":947,"passed_time":13.20482574,"remaining_time":0.7243153357},
{"learn":[0.4201265361],"iteration":948,"passed_time":13.21766481,"remaining_time":0.7103276136},
{"learn":[0.4201211919],"iteration":949,"passed_time":13.23082425,"remaining_time":0.6963591711},
{"learn":[0.4201143273],"iteration":950,"passed_time":13.24371286,"remaining_time":0.6823784757},
{"learn":[0.4201069005],"iteration":951,"passed_time":13.25854602,"remaining_time":0.6684981184},
{"learn":[0.4201020182],"iteration":952,"passed_time":13.27204091,"remaining_time":0.6545497614},
{"learn":[0.4200978506],"iteration":953,"passed_time":13.28623949,"remaining_time":0.6406362857},
{"learn":[0.4200925459],"iteration":954,"passed_time":13.29859549,"remaining_time":0.6266353896},
{"learn":[0.4200880854],"iteration":955,"passed_time":13.31241158,"remaining_time":0.6127051356},
{"learn":[0.4200832984],"iteration":956,"passed_time":13.32526899,"remaining_time":0.5987320445},
{"learn":[0.4200768682],"iteration":957,"passed_time":13.33936816,"remaining_time":0.584815723},
{"learn":[0.4200741579],"iteration":958,"passed_time":13.35322842,"remaining_time":0.5708888061},
{"learn":[0.4200672572],"iteration":959,"passed_time":13.36696876,"remaining_time":0.5569570317},
{"learn":[0.4200626497],"iteration":960,"passed_time":13.38045432,"remaining_time":0.5430153157},
{"learn":[0.4200566384],"iteration":961,"passed_time":13.39360147,"remaining_time":0.5290611806},
{"learn":[0.4200516855],"iteration":962,"passed_time":13.40682736,"remaining_time":0.5151117471},
{"learn":[0.4200477895],"iteration":963,"passed_time":13.41994289,"remaining_time":0.501159693},
{"learn":[0.4200438623],"iteration":964,"passed_time":13.43346236,"remaining_time":0.4872240236},
{"learn":[0.4200378092],"iteration":965,"passed_time":13.44689801,"remaining_time":0.4732862652},
{"learn":[0.4200322042],"iteration":966,"passed_time":13.45911247,"remaining_time":0.4593078713},
{"learn":[0.4200289364],"iteration":967,"passed_time":13.47232028,"remaining_time":0.4453659598},
{"learn":[0.4200228525],"iteration":968,"passed_time":13.48536148,"remaining_time":0.431420233},
{"learn":[0.4200173217],"iteration":969,"passed_time":13.49905328,"remaining_time":0.4174964932},
{"learn":[0.4200106834],"iteration":970,"passed_time":13.51313391,"remaining_time":0.4035848438},
{"learn":[0.4200058089],"iteration":971,"passed_time":13.526885,"remaining_time":0.389663354},
{"learn":[0.4199993755],"iteration":972,"passed_time":13.54013969,"remaining_time":0.3757284395},
{"learn":[0.4199953364],"iteration":973,"passed_time":13.55300851,"remaining_time":0.3617846215},
{"learn":[0.4199895945],"iteration":974,"passed_time":13.56569651,"remaining_time":0.347838372},
{"learn":[0.4199843503],"iteration":975,"passed_time":13.57916286,"remaining_time":0.3339138408},
{"learn":[0.4199797673],"iteration":976,"passed_time":13.59153394,"remaining_time":0.3199644633},
{"learn":[0.4199761389],"iteration":977,"passed_time":13.60491388,"remaining_time":0.3060410075},
{"learn":[0.4199697002],"iteration":978,"passed_time":13.61967382,"remaining_time":0.2921482638},
{"learn":[0.4199630978],"iteration":979,"passed_time":13.63369258,"remaining_time":0.278238624},
{"learn":[0.4199585225],"iteration":980,"passed_time":13.64857652,"remaining_time":0.2643455187},
{"learn":[0.4199525992],"iteration":981,"passed_time":13.66189912,"remaining_time":0.2504217762},
{"learn":[0.4199460018],"iteration":982,"passed_time":13.67565501,"remaining_time":0.2365067499},
{"learn":[0.4199425092],"iteration":983,"passed_time":13.68980342,"remaining_time":0.2225984297},
{"learn":[0.4199373243],"iteration":984,"passed_time":13.70205251,"remaining_time":0.2086606981},
{"learn":[0.4199318556],"iteration":985,"passed_time":13.71610472,"remaining_time":0.194751994},
{"learn":[0.4199254661],"iteration":986,"passed_time":13.72908329,"remaining_time":0.180828858},
{"learn":[0.4199186296],"iteration":987,"passed_time":13.74342862,"remaining_time":0.1669242343},
{"learn":[0.4199133764],"iteration":988,"passed_time":13.7574215,"remaining_time":0.1530147993},
{"learn":[0.4199081919],"iteration":989,"passed_time":13.77065707,"remaining_time":0.1390975461},
{"learn":[0.4199042018],"iteration":990,"passed_time":13.78306677,"remaining_time":0.1251741685},
{"learn":[0.4198988798],"iteration":991,"passed_time":13.79784993,"remaining_time":0.1112729833},
{"learn":[0.4198941701],"iteration":992,"passed_time":13.81138286,"remaining_time":0.09736120848},
{"learn":[0.4198881918],"iteration":993,"passed_time":13.82483954,"remaining_time":0.08344973567},
{"learn":[0.4198828891],"iteration":994,"passed_time":13.83784115,"remaining_time":0.06953689022},
{"learn":[0.4198780826],"iteration":995,"passed_time":13.85124221,"remaining_time":0.05562747877},
{"learn":[0.4198712196],"iteration":996,"passed_time":13.86404266,"remaining_time":0.04171727983},
{"learn":[0.4198641977],"iteration":997,"passed_time":13.87751989,"remaining_time":0.0278106611},
{"learn":[0.419856917],"iteration":998,"passed_time":13.8913329,"remaining_time":0.01390523814},
{"learn":[0.4198511917],"iteration":999,"passed_time":13.9040506,"remaining_time":0}
]}